[{"Id":[137900],"FirstName":["თამილა"],"LastName":["თეიმურაზიშვილი"],"Organisation":["შპს-ბავშვთა ჯანმრთელობის ცენტრი"],"Position":["ხელმძღვანელი"],"BirthPlace":["საქართველო, ქალაქი თელავი"],"BirthDate":["13.08.1953"],"VersionId":{},"DateEdited":["28.03.2022"],"DeclarationSubmitDate":["28.03.2022"],"FamilyMembers":[{"FirstName":["სოლომონ"],"LastName":["თეიმურაზიშვილი"],"BirthPlace":["საქართველო, კახეთი, თელავი"],"BirthDate":["03.09.1950"],"Relationship":["ძმა"],"Comment":{}},{"FirstName":["ზურაბ"],"LastName":["თეიმურაზიშვილი"],"BirthPlace":["საქართველო, კახეთი, თელავი"],"BirthDate":["31.07.1961"],"Relationship":["ძმა"],"Comment":{}},{"FirstName":["ნინო"],"LastName":["ჩხაიძე"],"BirthPlace":["საქართველო, გურია, ლანჩხუთი"],"BirthDate":["15.06.1961"],"Relationship":["ძმის მეუღლე"],"Comment":{}}],"Properties":[{"Address":[", , ქალაქი თბილისი , ქუჩა ელიზბარ მინდელი , N 12"],"Area":[77.8],"RegistrationDetails":{},"BlockList":{},"IsRegisteredInGeorgia":["რეგისტრირებულია საქართველოში"],"Share":[30],"PropertyType":["ბინა"],"PurchaseForm":["ნასყიდობა"],"PurchaseDate":["16.11.2015"],"PurchaseYear":{},"Price":[21000],"CurrencyName":["USD"],"Details":{},"Shareholders":[{"FirstName":["გიორგი"],"LastName":["თეიმურაზიშვილი"],"RelationShipName":[""],"Share":[0]}],"OwnerFirstName":["თამილა"],"OwnerLatsName":["თეიმურაზიშვილი"],"OwnerId":{},"Comment":{},"RelationName":[""]}],"MovableProperties":[],"Securities":[],"BankAccounts":[{"BankName":["ლიბერთი ბანკი"],"AccountType":["ანაბარი"],"Type":[1],"Currency":["GEL"],"Amount":[244.16],"OwnerFirstName":["თამილა"],"OwnerLatsName":["თეიმურაზიშვილი"],"OwnerId":{},"Comment":{},"RelationName":[""]},{"BankName":["საქართველოს ბანკი"],"AccountType":["სახელფასო"],"Type":[1],"Currency":["GEL"],"Amount":[1102.71],"OwnerFirstName":["თამილა"],"OwnerLatsName":["თეიმურაზიშვილი"],"OwnerId":{},"Comment":{},"RelationName":[""]},{"BankName":["საქართველოს ბანკი"],"AccountType":["ანაბარი"],"Type":[1],"Currency":["GEL"],"Amount":[43002],"OwnerFirstName":["თამილა"],"OwnerLatsName":["თეიმურაზიშვილი"],"OwnerId":{},"Comment":{},"RelationName":[""]},{"BankName":["\"საქართველოს ბანკი\""],"AccountType":["სახელფასო"],"Type":[1],"Currency":["GEL"],"Amount":[5582],"OwnerFirstName":["ნინო"],"OwnerLatsName":["ჩხაიძე"],"OwnerId":[30941],"Comment":{},"RelationName":[""]},{"BankName":["\"ლიბერთი ბანკი\""],"AccountType":["სახელფასო"],"Type":[1],"Currency":["GEL"],"Amount":[1215],"OwnerFirstName":["ზურაბ"],"OwnerLatsName":["თეიმურაზიშვილი"],"OwnerId":[30940],"Comment":{},"RelationName":[""]}],"Cashes":[],"Jobs":[{"Organisation":["თელავის შპს \"ბავშთა ჯანმრთელობის ცენტრი\" პოლიკლინიკური განყოფილება"],"Position":["ოჯახის ექიმი-პედიატრი"],"Amount":[10156],"Currency":["GEL"],"StartDate":["01.01.2021"],"EndDate":["31.12.2021"],"IsSecret":[false],"OwnerFirstName":["ნინო"],"OwnerLatsName":["ჩხაიძე"],"OwnerId":[30941],"Comment":{},"RelationName":[""]},{"Organisation":["სოციალური მომსახურების სააგენტო, კახეთის სამხარეო ცენტრი"],"Position":["შტატგარეშე თანამშრომელი"],"Amount":[6760],"Currency":["GEL"],"StartDate":["01.02.2021"],"EndDate":["31.12.2021"],"IsSecret":[false],"OwnerFirstName":["ნინო"],"OwnerLatsName":["ჩხაიძე"],"OwnerId":[30941],"Comment":{},"RelationName":[""]},{"Organisation":["შპს საქართველოს გაერთიანებული წყალმომარაგების კომპანია"],"Position":["ჩქარი ფილრების მორიგე ოპერატორი"],"Amount":[4800],"Currency":["GEL"],"StartDate":["01.01.2021"],"EndDate":["31.12.2021"],"IsSecret":[false],"OwnerFirstName":["ზურაბ"],"OwnerLatsName":["თეიმურაზიშვილი"],"OwnerId":[30940],"Comment":{},"RelationName":[""]},{"Organisation":["აიპ სპორტულ კლუბთა გაერთიანება"],"Position":["საჭადრაკო კლუბის მენეჯერი"],"Amount":[7200],"Currency":["GEL"],"StartDate":["01.01.2021"],"EndDate":["31.12.2021"],"IsSecret":[false],"OwnerFirstName":["ზურაბ"],"OwnerLatsName":["თეიმურაზიშვილი"],"OwnerId":[30940],"Comment":{},"RelationName":[""]},{"Organisation":["შპს ბავშვთა ჯანმრთელობის ცენტრი"],"Position":["შპს ცენტრის დირექტორი"],"Amount":[30449.34],"Currency":["GEL"],"StartDate":["01.01.2021"],"EndDate":["31.12.2021"],"IsSecret":[false],"OwnerFirstName":["თამილა"],"OwnerLatsName":["თეიმურაზიშვილი"],"OwnerId":{},"Comment":["აღნიშნულ თანხაში შედის ცენტრის დირექტორის და  ბავშვთა რეაბილიტაციის პროგრამის კოორდინატორის პოზიციებზე მიღებული შემოსავალი ჯამურად."],"RelationName":[""]}],"Contracts":[{"ContractType":["სესხი"],"Subject":["ბინის რემონტი"],"Amount":[7867.73],"AmountCurrency":{},"Currency":["GEL"],"StartDate":["17.05.2019"],"EffectiveDate":["02.09.2019"],"EndDate":["02.05.2022"],"EndDateName":["02.05.2022"],"Agency":["ბანკი"],"Type":[2],"Income":[1386.27],"IncomeCurrency":["GEL"],"OwnerFirstName":["ნინო"],"OwnerLatsName":["ჩხაიძე"],"OwnerId":[30941],"Comment":{},"RelationName":[""]}],"Gifts":[],"InOuts":[],"Enterprice":[],"LinkedEnterprice":[],"DeclarationHistory":{"DeclarantInfoHistory":[],"FamilyMemberHistory":[],"PropertyHistory":[],"MovablePropertyHistory":[],"SecurityHistory":[],"BankAccountHistory":[],"CashHistory":[],"EnterpriseHistory":[],"LinkedEnterpriseHistory":[],"JobHistory":[],"ContractHistory":[],"GiftHistory":[],"InOutHistory":[]}},{"Id":[130922],"FirstName":["თამილა"],"LastName":["თეიმურაზიშვილი"],"Organisation":["შპს-ბავშვთა ჯანმრთელობის ცენტრი"],"Position":["ხელმძღვანელი"],"BirthPlace":["საქართველო, ქალაქი თელავი"],"BirthDate":["13.08.1953"],"VersionId":{},"DateEdited":{},"DeclarationSubmitDate":["26.03.2021"],"FamilyMembers":[{"FirstName":["ქრისტინე"],"LastName":["თეიმურაზიშვილი"],"BirthPlace":["საქართველო, კახეთი, თელავი, სოფ.სანიორე"],"BirthDate":["22.12.1927"],"Relationship":["დედა"],"Comment":{}},{"FirstName":["სოლომონ"],"LastName":["თეიმურაზიშვილი"],"BirthPlace":["საქართველო, კახეთი, თელავი"],"BirthDate":["03.09.1950"],"Relationship":["ძმა"],"Comment":{}},{"FirstName":["ზურაბ"],"LastName":["თეიმურაზიშვილი"],"BirthPlace":["საქართველო, კახეთი, თელავი"],"BirthDate":["31.07.1961"],"Relationship":["ძმა"],"Comment":{}},{"FirstName":["ნინო"],"LastName":["ჩხაიძე"],"BirthPlace":["საქართველო, გურია, ლანჩხუთი"],"BirthDate":["15.06.1961"],"Relationship":["ძმის მეუღლე"],"Comment":{}}],"Properties":[{"Address":["საქართველო, ქალაქი თელავის მუნიციპალიტეტი, თბილისის ქუჩა #24"],"Area":[102],"RegistrationDetails":{},"BlockList":{},"IsRegisteredInGeorgia":{},"Share":[100],"PropertyType":["საცხოვრებელი სახლი"],"PurchaseForm":["მემკვიდრეობა"],"PurchaseDate":["01.01.1900"],"PurchaseYear":[2010],"Price":[0],"CurrencyName":["GEL"],"Details":{},"Shareholders":[],"OwnerFirstName":["ქრისტინე"],"OwnerLatsName":["თეიმურაზიშვილი"],"OwnerId":[30938],"Comment":{},"RelationName":[""]},{"Address":["საქართველო, ქალაქი თბილისი, მინდელის #12, სართული 8, ბინა#56, ბლოკი2"],"Area":[77.8],"RegistrationDetails":{},"BlockList":{},"IsRegisteredInGeorgia":{},"Share":[30],"PropertyType":["ბინა"],"PurchaseForm":["ყიდვა"],"PurchaseDate":["01.01.1900"],"PurchaseYear":[2015],"Price":[21000],"CurrencyName":["USD"],"Details":{},"Shareholders":[{"FirstName":["გიორგი"],"LastName":["თეიმურაზიშვილი"],"RelationShipName":[""],"Share":[0]}],"OwnerFirstName":["თამილა"],"OwnerLatsName":["თეიმურაზიშვილი"],"OwnerId":{},"Comment":{},"RelationName":[""]},{"Address":["საქართველო, თელავის რაიონი, სოფ. ვარდისუბანი, თელავის რაიონი, სოფ.ვარდისუბანი"],"Area":[1477.63],"RegistrationDetails":{},"BlockList":{},"IsRegisteredInGeorgia":{},"Share":[100],"PropertyType":["მიწის ნაკვეთი"],"PurchaseForm":["უსასყიდლოდ სახელწიფოს მიერ"],"PurchaseDate":["01.01.1900"],"PurchaseYear":[1999],"Price":[0],"CurrencyName":["GEL"],"Details":{},"Shareholders":[],"OwnerFirstName":["თამილა"],"OwnerLatsName":["თეიმურაზიშვილი"],"OwnerId":{},"Comment":{},"RelationName":[""]},{"Address":["საქართველო, კახეთი, თელავი, თბილისის ქ#24"],"Area":[606],"RegistrationDetails":{},"BlockList":{},"IsRegisteredInGeorgia":{},"Share":[100],"PropertyType":["მიწის ნაკვეთი"],"PurchaseForm":["მემკვიდრეობა"],"PurchaseDate":["01.01.1900"],"PurchaseYear":[2010],"Price":[0],"CurrencyName":["GEL"],"Details":{},"Shareholders":[],"OwnerFirstName":["ქრისტინე"],"OwnerLatsName":["თეიმურაზიშვილი"],"OwnerId":[30938],"Comment":{},"RelationName":[""]},{"Address":["საქართველო, კახეთი, თელავი,სოფ.ვარდისუბანი, კახეთი, თელავი, სოფ.ვარდისუბანი"],"Area":[2947],"RegistrationDetails":{},"BlockList":{},"IsRegisteredInGeorgia":{},"Share":[100],"PropertyType":["მიწის ნაკვეთი"],"PurchaseForm":["მემკვიდრეობა"],"PurchaseDate":["01.01.1900"],"PurchaseYear":[2010],"Price":[0],"CurrencyName":["GEL"],"Details":{},"Shareholders":[],"OwnerFirstName":["ქრისტინე"],"OwnerLatsName":["თეიმურაზიშვილი"],"OwnerId":[30938],"Comment":{},"RelationName":[""]}],"MovableProperties":[],"Securities":[],"BankAccounts":[{"BankName":["ლიბერთი ბანკი"],"AccountType":["ანაბარი"],"Type":[1],"Currency":["GEL"],"Amount":[7331],"OwnerFirstName":["თამილა"],"OwnerLatsName":["თეიმურაზიშვილი"],"OwnerId":{},"Comment":{},"RelationName":[""]},{"BankName":["საქართველოს ბანკი"],"AccountType":["სახელფასო"],"Type":[1],"Currency":["GEL"],"Amount":[2106],"OwnerFirstName":["თამილა"],"OwnerLatsName":["თეიმურაზიშვილი"],"OwnerId":{},"Comment":{},"RelationName":[""]},{"BankName":["საქართველოს ბანკი"],"AccountType":["ანაბარი"],"Type":[1],"Currency":["GEL"],"Amount":[26026],"OwnerFirstName":["თამილა"],"OwnerLatsName":["თეიმურაზიშვილი"],"OwnerId":{},"Comment":{},"RelationName":[""]},{"BankName":["\"საქართველოს ბანკი\""],"AccountType":["სახელფასო"],"Type":[1],"Currency":["GEL"],"Amount":[4486.73],"OwnerFirstName":["ნინო"],"OwnerLatsName":["ჩხაიძე"],"OwnerId":[30941],"Comment":{},"RelationName":[""]},{"BankName":["\"ლიბერთი ბანკი\""],"AccountType":["სახელფასო"],"Type":[1],"Currency":["GEL"],"Amount":[600],"OwnerFirstName":["ზურაბ"],"OwnerLatsName":["თეიმურაზიშვილი"],"OwnerId":[30940],"Comment":{},"RelationName":[""]}],"Cashes":[],"Jobs":[{"Organisation":["თელავის შპს 'ბავშვთა ჯანმრთელობის ცენტრი\""],"Position":["დირექტორი"],"Amount":[29760],"Currency":["GEL"],"StartDate":["01.01.2020"],"EndDate":["31.12.2020"],"IsSecret":[false],"OwnerFirstName":["თამილა"],"OwnerLatsName":["თეიმურაზიშვილი"],"OwnerId":{},"Comment":{},"RelationName":[""]},{"Organisation":["თელავის შპს \"ბავშვთა ჯანმრთელობის ცენტრი\" რებილიტაციური განყოფილება"],"Position":["სოციალური რეაბილიტაციის და ბავშვზე ზრუნვის სახელმწიფო პროგრამის ბავშვთა რეაბილიტაციის ქვეპროგრამის კოორდინატორი"],"Amount":[6670],"Currency":["GEL"],"StartDate":["01.01.2020"],"EndDate":["31.12.2020"],"IsSecret":[false],"OwnerFirstName":["თამილა"],"OwnerLatsName":["თეიმურაზიშვილი"],"OwnerId":{},"Comment":{},"RelationName":[""]},{"Organisation":["თელავის შპს \"ბავშვთა ჯანმრთელობის ცენტრი\" პოლიკლინიკური განყოფილება"],"Position":["პედიატრი"],"Amount":[14143],"Currency":["GEL"],"StartDate":["01.01.2020"],"EndDate":["31.12.2020"],"IsSecret":[false],"OwnerFirstName":["ნინო"],"OwnerLatsName":["ჩხაიძე"],"OwnerId":[30941],"Comment":{},"RelationName":[""]},{"Organisation":["სოციალური მომსახურების სააგენტო, კახეთის სამხარეო ცენტრი"],"Position":["შტატგარეშე თანამშრომელი"],"Amount":[8450],"Currency":["GEL"],"StartDate":["01.01.2020"],"EndDate":["31.12.2020"],"IsSecret":[false],"OwnerFirstName":["ნინო"],"OwnerLatsName":["ჩხაიძე"],"OwnerId":[30941],"Comment":{},"RelationName":[""]},{"Organisation":["შპს საქართველოს გაერთიანებული წყალმომარაგების კომპანია"],"Position":["ჩქარი ფილტრების მორიგე ოპერატორი"],"Amount":[6000],"Currency":["GEL"],"StartDate":["01.01.2020"],"EndDate":["31.12.2020"],"IsSecret":[false],"OwnerFirstName":["ზურაბ"],"OwnerLatsName":["თეიმურაზიშვილი"],"OwnerId":[30940],"Comment":{},"RelationName":[""]},{"Organisation":["აიპ სპორტულ კლუბთა გაერთიანება თელავი"],"Position":["საჭადრაკო კლუბის მენეჯერი"],"Amount":[9000],"Currency":["GEL"],"StartDate":["01.01.2020"],"EndDate":["31.12.2020"],"IsSecret":[false],"OwnerFirstName":["ზურაბ"],"OwnerLatsName":["თეიმურაზიშვილი"],"OwnerId":[30940],"Comment":{},"RelationName":[""]},{"Organisation":["\"ფაინ თრი ინტერნეიშენალ\""],"Position":["კონსულტანტი"],"Amount":[3600],"Currency":["GEL"],"StartDate":["01.01.2020"],"EndDate":["31.12.2020"],"IsSecret":[false],"OwnerFirstName":["ნინო"],"OwnerLatsName":["ჩხაიძე"],"OwnerId":[30941],"Comment":{},"RelationName":[""]}],"Contracts":[{"ContractType":["სესხი"],"Subject":["ბინის რემონტი"],"Amount":[7867.73],"AmountCurrency":{},"Currency":["GEL"],"StartDate":["17.05.2019"],"EffectiveDate":["02.09.2019"],"EndDate":["02.05.2022"],"EndDateName":["02.05.2022"],"Agency":["საქართველოს ბანკი"],"Type":[2],"Income":[1362.73],"IncomeCurrency":["GEL"],"OwnerFirstName":["ნინო"],"OwnerLatsName":["ჩხაიძე"],"OwnerId":[30941],"Comment":{},"RelationName":[""]}],"Gifts":[],"InOuts":[],"Enterprice":[],"LinkedEnterprice":[],"DeclarationHistory":{}},{"Id":[124910],"FirstName":["თამილა"],"LastName":["თეიმურაზიშვილი"],"Organisation":["შპს-ბავშვთა ჯანმრთელობის ცენტრი"],"Position":["ხელმძღვანელი"],"BirthPlace":["საქართველო, ქალაქი თელავი"],"BirthDate":["13.08.1953"],"VersionId":{},"DateEdited":{},"DeclarationSubmitDate":["28.03.2020"],"FamilyMembers":[{"FirstName":["ქრისტინე"],"LastName":["თეიმურაზიშვილი"],"BirthPlace":["საქართველო, კახეთი, თელავი, სოფ.სანიორე"],"BirthDate":["22.12.1927"],"Relationship":["დედა"],"Comment":{}},{"FirstName":["სოლომონ"],"LastName":["თეიმურაზიშვილი"],"BirthPlace":["საქართველო, კახეთი, თელავი"],"BirthDate":["03.09.1950"],"Relationship":["ძმა"],"Comment":{}},{"FirstName":["ზურაბ"],"LastName":["თეიმურაზიშვილი"],"BirthPlace":["საქართველო, კახეთი, თელავი"],"BirthDate":["31.07.1961"],"Relationship":["ძმა"],"Comment":{}},{"FirstName":["ნინო"],"LastName":["ჩხაიძე"],"BirthPlace":["საქართველო, გურია, ლანჩხუთი"],"BirthDate":["15.06.1961"],"Relationship":["ძმის მეუღლე"],"Comment":{}}],"Properties":[{"Address":["საქართველო, ქალაქი თელავის მუნიციპალიტეტი, თბილისის ქუჩა #24"],"Area":[102],"RegistrationDetails":{},"BlockList":{},"IsRegisteredInGeorgia":{},"Share":[100],"PropertyType":["საცხოვრებელი სახლი"],"PurchaseForm":["მემკვიდრეობა"],"PurchaseDate":["01.01.1900"],"PurchaseYear":[2010],"Price":[0],"CurrencyName":["GEL"],"Details":{},"Shareholders":[],"OwnerFirstName":["ქრისტინე"],"OwnerLatsName":["თეიმურაზიშვილი"],"OwnerId":[30938],"Comment":{},"RelationName":[""]},{"Address":["საქართველო, ქალაქი თბილისი, ანა პოლიტკოვსკაიას #5, სართული 8, ბინა#56, ბლოკი2"],"Area":[77.8],"RegistrationDetails":{},"BlockList":{},"IsRegisteredInGeorgia":{},"Share":[30],"PropertyType":["ბინა"],"PurchaseForm":["ყიდვა"],"PurchaseDate":["01.01.1900"],"PurchaseYear":[2015],"Price":[21000],"CurrencyName":["USD"],"Details":{},"Shareholders":[{"FirstName":["გიორგი"],"LastName":["თეიმურაზიშვილი"],"RelationShipName":[""],"Share":[0]}],"OwnerFirstName":["თამილა"],"OwnerLatsName":["თეიმურაზიშვილი"],"OwnerId":{},"Comment":{},"RelationName":[""]},{"Address":["საქართველო, თელავის რაიონი, სოფ. ვარდისუბანი, თელავის რაიონი, სოფ.ვარდისუბანი"],"Area":[1477.63],"RegistrationDetails":{},"BlockList":{},"IsRegisteredInGeorgia":{},"Share":[100],"PropertyType":["მიწის ნაკვეთი"],"PurchaseForm":["უსასყიდლოდ სახელწიფოს მიერ"],"PurchaseDate":["01.01.1900"],"PurchaseYear":[1999],"Price":[0],"CurrencyName":["GEL"],"Details":{},"Shareholders":[],"OwnerFirstName":["თამილა"],"OwnerLatsName":["თეიმურაზიშვილი"],"OwnerId":{},"Comment":{},"RelationName":[""]},{"Address":["საქართველო, კახეთი, თელავი, თბილისის ქ#24"],"Area":[606],"RegistrationDetails":{},"BlockList":{},"IsRegisteredInGeorgia":{},"Share":[100],"PropertyType":["მიწის ნაკვეთი"],"PurchaseForm":["მემკვიდრეობა"],"PurchaseDate":["01.01.1900"],"PurchaseYear":[2010],"Price":[0],"CurrencyName":["GEL"],"Details":{},"Shareholders":[],"OwnerFirstName":["ქრისტინე"],"OwnerLatsName":["თეიმურაზიშვილი"],"OwnerId":[30938],"Comment":{},"RelationName":[""]},{"Address":["საქართველო, კახეთი, თელავი,სოფ.ვარდისუბანი, კახეთი, თელავი, სოფ.ვარდისუბანი"],"Area":[2947],"RegistrationDetails":{},"BlockList":{},"IsRegisteredInGeorgia":{},"Share":[100],"PropertyType":["მიწის ნაკვეთი"],"PurchaseForm":["მემკვიდრეობა"],"PurchaseDate":["01.01.1900"],"PurchaseYear":[2010],"Price":[0],"CurrencyName":["GEL"],"Details":{},"Shareholders":[],"OwnerFirstName":["ქრისტინე"],"OwnerLatsName":["თეიმურაზიშვილი"],"OwnerId":[30938],"Comment":{},"RelationName":[""]}],"MovableProperties":[],"Securities":[],"BankAccounts":[{"BankName":["ლიბერთი ბანკი"],"AccountType":["ანაბარი"],"Type":[1],"Currency":["GEL"],"Amount":[6788],"OwnerFirstName":["თამილა"],"OwnerLatsName":["თეიმურაზიშვილი"],"OwnerId":{},"Comment":{},"RelationName":[""]},{"BankName":["საქართველოს ბანკი"],"AccountType":["სახელფასო"],"Type":[1],"Currency":["GEL"],"Amount":[4563],"OwnerFirstName":["თამილა"],"OwnerLatsName":["თეიმურაზიშვილი"],"OwnerId":{},"Comment":{},"RelationName":[""]},{"BankName":["საქართველოს ბანკი"],"AccountType":["ანაბარი"],"Type":[1],"Currency":["GEL"],"Amount":[15551],"OwnerFirstName":["თამილა"],"OwnerLatsName":["თეიმურაზიშვილი"],"OwnerId":{},"Comment":{},"RelationName":[""]},{"BankName":["\"საქართველოს ბანკი\""],"AccountType":["სახელფასო"],"Type":[1],"Currency":["GEL"],"Amount":[2000],"OwnerFirstName":["ნინო"],"OwnerLatsName":["ჩხაიძე"],"OwnerId":[30941],"Comment":{},"RelationName":[""]},{"BankName":["\"საქართველოს ბანკი\""],"AccountType":["სახელფასო"],"Type":[1],"Currency":["GEL"],"Amount":[670],"OwnerFirstName":["ზურაბ"],"OwnerLatsName":["თეიმურაზიშვილი"],"OwnerId":[30940],"Comment":{},"RelationName":[""]}],"Cashes":[],"Jobs":[{"Organisation":["თელავის შპს 'ბავშვთა ჯანმრთელობის ცენტრი\""],"Position":["დირექტორი"],"Amount":[29400],"Currency":["GEL"],"StartDate":["01.01.2019"],"EndDate":["31.12.2019"],"IsSecret":[false],"OwnerFirstName":["თამილა"],"OwnerLatsName":["თეიმურაზიშვილი"],"OwnerId":{},"Comment":{},"RelationName":[""]},{"Organisation":["თელავის შპს \"ბავშვთა ჯანმრთელობის ცენტრი\" რებილიტაციური განყოფილება"],"Position":["სოციალური რეაბილიტაციის და ბავშვზე ზრუნვის სახელმწიფო პროგრამის ბავშვთა რეაბილიტაციის ქვეპროგრამის კოორდინატორი"],"Amount":[4100],"Currency":["GEL"],"StartDate":["01.01.2019"],"EndDate":["31.12.2019"],"IsSecret":[false],"OwnerFirstName":["თამილა"],"OwnerLatsName":["თეიმურაზიშვილი"],"OwnerId":{},"Comment":{},"RelationName":[""]},{"Organisation":["თელავის შპს \"ბავშვთა ჯანმრთელობის ცენტრი\" პოლიკლინიკური განყოფილება"],"Position":["ოჯახის ექიმი-პედიატრი"],"Amount":[13390],"Currency":["GEL"],"StartDate":["01.01.2019"],"EndDate":["31.12.2019"],"IsSecret":[false],"OwnerFirstName":["ნინო"],"OwnerLatsName":["ჩხაიძე"],"OwnerId":[30941],"Comment":{},"RelationName":[""]},{"Organisation":["სოციალური მომსახურების სააგენტო, კახეთის სამხარეო ცენტრი"],"Position":["შტატგარეშე თანამშრომელი"],"Amount":[8450],"Currency":["GEL"],"StartDate":["01.01.2019"],"EndDate":["31.12.2019"],"IsSecret":[false],"OwnerFirstName":["ნინო"],"OwnerLatsName":["ჩხაიძე"],"OwnerId":[30941],"Comment":{},"RelationName":[""]},{"Organisation":["შპს საქართველოს გაერთიანებული წყალმომარაგების კომპანია"],"Position":["ჩქარი ფილტრების მორიგე ოპერატორი"],"Amount":[6000],"Currency":["GEL"],"StartDate":["01.01.2019"],"EndDate":["31.12.2019"],"IsSecret":[false],"OwnerFirstName":["ზურაბ"],"OwnerLatsName":["თეიმურაზიშვილი"],"OwnerId":[30940],"Comment":{},"RelationName":[""]},{"Organisation":["აიპ სპორტულ კლუბთა გაერთიანება თელავი"],"Position":["საჭადრაკო კლუბის მენეჯერი"],"Amount":[9000],"Currency":["GEL"],"StartDate":["01.01.2019"],"EndDate":["31.12.2019"],"IsSecret":[false],"OwnerFirstName":["ზურაბ"],"OwnerLatsName":["თეიმურაზიშვილი"],"OwnerId":[30940],"Comment":{},"RelationName":[""]}],"Contracts":[{"ContractType":["სესხი"],"Subject":["ბინის რემონტი"],"Amount":[7867.73],"AmountCurrency":{},"Currency":["GEL"],"StartDate":["17.05.2019"],"EffectiveDate":["02.09.2019"],"EndDate":["02.05.2022"],"EndDateName":["02.05.2022"],"Agency":["საქართველოს ბანკი"],"Type":[2],"Income":[2100],"IncomeCurrency":["GEL"],"OwnerFirstName":["ნინო"],"OwnerLatsName":["ჩხაიძე"],"OwnerId":[30941],"Comment":{},"RelationName":[""]}],"Gifts":[],"InOuts":[],"Enterprice":[],"LinkedEnterprice":[],"DeclarationHistory":{}},{"Id":[118237],"FirstName":["თამილა"],"LastName":["თეიმურაზიშვილი"],"Organisation":["შპს-ბავშვთა ჯანმრთელობის ცენტრი"],"Position":["ხელმძღვანელი"],"BirthPlace":["საქართველო, ქალაქი თელავი"],"BirthDate":["13.08.1953"],"VersionId":{},"DateEdited":{},"DeclarationSubmitDate":["26.03.2019"],"FamilyMembers":[{"FirstName":["ქრისტინე"],"LastName":["თეიმურაზიშვილი"],"BirthPlace":["საქართველო, კახეთი, თელავი, სოფ.სანიორე"],"BirthDate":["22.12.1927"],"Relationship":["დედა"],"Comment":{}},{"FirstName":["სოლომონ"],"LastName":["თეიმურაზიშვილი"],"BirthPlace":["საქართველო, კახეთი, თელავი"],"BirthDate":["03.09.1950"],"Relationship":["ძმა"],"Comment":{}},{"FirstName":["ზურაბ"],"LastName":["თეიმურაზიშვილი"],"BirthPlace":["საქართველო, კახეთი, თელავი"],"BirthDate":["31.07.1961"],"Relationship":["ძმა"],"Comment":{}},{"FirstName":["ნინო"],"LastName":["ჩხაიძე"],"BirthPlace":["საქართველო, გურია, ლანჩხუთი"],"BirthDate":["15.06.1961"],"Relationship":["ძმის მეუღლე"],"Comment":{}}],"Properties":[{"Address":["საქართველო, ქალაქი თელავის მუნიციპალიტეტი, თბილისის ქუჩა #24"],"Area":[102],"RegistrationDetails":{},"BlockList":{},"IsRegisteredInGeorgia":{},"Share":[100],"PropertyType":["საცხოვრებელი სახლი"],"PurchaseForm":["მემკვიდრეობა"],"PurchaseDate":["01.01.1900"],"PurchaseYear":[2010],"Price":[0],"CurrencyName":["GEL"],"Details":{},"Shareholders":[],"OwnerFirstName":["ქრისტინე"],"OwnerLatsName":["თეიმურაზიშვილი"],"OwnerId":[30938],"Comment":{},"RelationName":[""]},{"Address":["საქართველო, ქალაქი თბილისი, ანა პოლიტკოვსკაიას #5, სართული 8, ბინა#56, ბლოკი2"],"Area":[77.8],"RegistrationDetails":{},"BlockList":{},"IsRegisteredInGeorgia":{},"Share":[30],"PropertyType":["ბინა"],"PurchaseForm":["ყიდვა"],"PurchaseDate":["01.01.1900"],"PurchaseYear":[2015],"Price":[21000],"CurrencyName":["USD"],"Details":{},"Shareholders":[{"FirstName":["გიორგი"],"LastName":["თეიმურაზიშვილი"],"RelationShipName":[""],"Share":[0]}],"OwnerFirstName":["თამილა"],"OwnerLatsName":["თეიმურაზიშვილი"],"OwnerId":{},"Comment":{},"RelationName":[""]},{"Address":["საქართველო, თელავის რაიონი, სოფ. ვარდისუბანი, თელავის რაიონი, სოფ.ვარდისუბანი"],"Area":[1477.63],"RegistrationDetails":{},"BlockList":{},"IsRegisteredInGeorgia":{},"Share":[100],"PropertyType":["მიწის ნაკვეთი"],"PurchaseForm":["უსასყიდლოდ სახელწიფოს მიერ"],"PurchaseDate":["01.01.1900"],"PurchaseYear":[1999],"Price":[0],"CurrencyName":["GEL"],"Details":{},"Shareholders":[],"OwnerFirstName":["თამილა"],"OwnerLatsName":["თეიმურაზიშვილი"],"OwnerId":{},"Comment":{},"RelationName":[""]},{"Address":["საქართველო, კახეთი, თელავი, თბილისის ქ#24"],"Area":[606],"RegistrationDetails":{},"BlockList":{},"IsRegisteredInGeorgia":{},"Share":[100],"PropertyType":["მიწის ნაკვეთი"],"PurchaseForm":["მემკვიდრეობა"],"PurchaseDate":["01.01.1900"],"PurchaseYear":[2010],"Price":[0],"CurrencyName":["GEL"],"Details":{},"Shareholders":[],"OwnerFirstName":["ქრისტინე"],"OwnerLatsName":["თეიმურაზიშვილი"],"OwnerId":[30938],"Comment":{},"RelationName":[""]},{"Address":["საქართველო, კახეთი, თელავი,სოფ.ვარდისუბანი, კახეთი, თელავი, სოფ.ვარდისუბანი"],"Area":[2947],"RegistrationDetails":{},"BlockList":{},"IsRegisteredInGeorgia":{},"Share":[100],"PropertyType":["მიწის ნაკვეთი"],"PurchaseForm":["მემკვიდრეობა"],"PurchaseDate":["01.01.1900"],"PurchaseYear":[2010],"Price":[0],"CurrencyName":["GEL"],"Details":{},"Shareholders":[],"OwnerFirstName":["ქრისტინე"],"OwnerLatsName":["თეიმურაზიშვილი"],"OwnerId":[30938],"Comment":{},"RelationName":[""]}],"MovableProperties":[],"Securities":[],"BankAccounts":[{"BankName":["ლიბერთი ბანკი"],"AccountType":["ანაბარი"],"Type":[1],"Currency":["GEL"],"Amount":[6327],"OwnerFirstName":["თამილა"],"OwnerLatsName":["თეიმურაზიშვილი"],"OwnerId":{},"Comment":{},"RelationName":[""]},{"BankName":["საქართველოს ბანკი"],"AccountType":["სახელფასო"],"Type":[1],"Currency":["GEL"],"Amount":[2515],"OwnerFirstName":["თამილა"],"OwnerLatsName":["თეიმურაზიშვილი"],"OwnerId":{},"Comment":{},"RelationName":[""]},{"BankName":["საქართველოს ბანკი"],"AccountType":["ანაბარი"],"Type":[1],"Currency":["GEL"],"Amount":[11420.88],"OwnerFirstName":["თამილა"],"OwnerLatsName":["თეიმურაზიშვილი"],"OwnerId":{},"Comment":{},"RelationName":[""]},{"BankName":["\"საქართველოს ბანკი\""],"AccountType":["სახელფასო"],"Type":[1],"Currency":["GEL"],"Amount":[1122],"OwnerFirstName":["ნინო"],"OwnerLatsName":["ჩხაიძე"],"OwnerId":[30941],"Comment":{},"RelationName":[""]},{"BankName":["\"საქართველოს ბანკი\""],"AccountType":["სახელფასო"],"Type":[1],"Currency":["GEL"],"Amount":[30],"OwnerFirstName":["ზურაბ"],"OwnerLatsName":["თეიმურაზიშვილი"],"OwnerId":[30940],"Comment":{},"RelationName":[""]}],"Cashes":[],"Jobs":[{"Organisation":["თელავის შპს 'ბავშვთა ჯანმრთელობის ცენტრი\""],"Position":["დირექტორი"],"Amount":[20820],"Currency":["GEL"],"StartDate":["01.01.2018"],"EndDate":["31.12.2018"],"IsSecret":[false],"OwnerFirstName":["თამილა"],"OwnerLatsName":["თეიმურაზიშვილი"],"OwnerId":{},"Comment":{},"RelationName":[""]},{"Organisation":["თელავის შპს \"ბავშვთა ჯანმრთელობის ცენტრი\" რებილიტაციური განყოფილება"],"Position":["სოციალური რეაბილიტაციის და ბავშვზე ზრუნვის სახელმწიფო პროგრამის ბავშვთა რეაბილიტაციის ქვეპროგრამის კოორდინატორი"],"Amount":[7813],"Currency":["GEL"],"StartDate":["01.01.2018"],"EndDate":["31.12.2018"],"IsSecret":[false],"OwnerFirstName":["თამილა"],"OwnerLatsName":["თეიმურაზიშვილი"],"OwnerId":{},"Comment":{},"RelationName":[""]},{"Organisation":["თელავის შპს \"ბავშვთა ჯანმრთელობის ცენტრი\" პოლიკლინიკური განყოფილება"],"Position":["ოჯახის ექიმი-პედიატრი"],"Amount":[9806.5],"Currency":["GEL"],"StartDate":["01.01.2018"],"EndDate":["31.12.2018"],"IsSecret":[false],"OwnerFirstName":["ნინო"],"OwnerLatsName":["ჩხაიძე"],"OwnerId":[30941],"Comment":{},"RelationName":[""]},{"Organisation":["სოციალური მომსახურების სააგენტო, კახეთის სამხარეო ცენტრი"],"Position":["შტატგარეშე თანამშრომელი"],"Amount":[8450],"Currency":["GEL"],"StartDate":["01.01.2018"],"EndDate":["31.12.2018"],"IsSecret":[false],"OwnerFirstName":["ნინო"],"OwnerLatsName":["ჩხაიძე"],"OwnerId":[30941],"Comment":{},"RelationName":[""]},{"Organisation":["შპს საქართველოს გაერთიანებული წყალმომარაგების კომპანია"],"Position":["ჩქარი ფილტრების მორიგე ოპერატორი"],"Amount":[6000],"Currency":["GEL"],"StartDate":["01.01.2018"],"EndDate":["31.12.2018"],"IsSecret":[false],"OwnerFirstName":["ზურაბ"],"OwnerLatsName":["თეიმურაზიშვილი"],"OwnerId":[30940],"Comment":{},"RelationName":[""]},{"Organisation":["აიპ სპორტულ კლუბთა გაერთიანება თელავი"],"Position":["საჭადრაკო კლუბის მენეჯერი"],"Amount":[9000],"Currency":["GEL"],"StartDate":["01.01.2018"],"EndDate":["31.12.2018"],"IsSecret":[false],"OwnerFirstName":["ზურაბ"],"OwnerLatsName":["თეიმურაზიშვილი"],"OwnerId":[30940],"Comment":{},"RelationName":[""]},{"Organisation":["შპს \"მზიური\""],"Position":["სამედიცინო კონსულტანტი"],"Amount":[4500],"Currency":["GEL"],"StartDate":["01.01.2018"],"EndDate":["31.12.2018"],"IsSecret":[false],"OwnerFirstName":["ნინო"],"OwnerLatsName":["ჩხაიძე"],"OwnerId":[30941],"Comment":{},"RelationName":[""]}],"Contracts":[{"ContractType":["სესხი"],"Subject":["ბინის რემონტი"],"Amount":[8120],"AmountCurrency":{},"Currency":["GEL"],"StartDate":["14.06.2016"],"EffectiveDate":["14.06.2016"],"EndDate":["03.06.2019"],"EndDateName":["03.06.2019"],"Agency":["საქართველოს ბანკი"],"Type":[2],"Income":[3927.24],"IncomeCurrency":["GEL"],"OwnerFirstName":["ნინო"],"OwnerLatsName":["ჩხაიძე"],"OwnerId":[30941],"Comment":{},"RelationName":[""]}],"Gifts":[],"InOuts":[],"Enterprice":[],"LinkedEnterprice":[],"DeclarationHistory":{}},{"Id":[109602],"FirstName":["თამილა"],"LastName":["თეიმურაზიშვილი"],"Organisation":["შპს-ბავშვთა ჯანმრთელობის ცენტრი"],"Position":["ხელმძღვანელი"],"BirthPlace":["საქართველო, ქალაქი თელავი"],"BirthDate":["13.08.1953"],"VersionId":{},"DateEdited":{},"DeclarationSubmitDate":["29.03.2018"],"FamilyMembers":[{"FirstName":["ქრისტინე"],"LastName":["თეიმურაზიშვილი"],"BirthPlace":["საქართველო, კახეთი, თელავი, სოფ.სანიორე"],"BirthDate":["22.12.1927"],"Relationship":["დედა"],"Comment":{}},{"FirstName":["სოლომონ"],"LastName":["თეიმურაზიშვილი"],"BirthPlace":["საქართველო, კახეთი, თელავი"],"BirthDate":["03.09.1950"],"Relationship":["ძმა"],"Comment":{}},{"FirstName":["ზურაბ"],"LastName":["თეიმურაზიშვილი"],"BirthPlace":["საქართველო, კახეთი, თელავი"],"BirthDate":["31.07.1961"],"Relationship":["ძმა"],"Comment":{}},{"FirstName":["ნინო"],"LastName":["ჩხაიძე"],"BirthPlace":["საქართველო, გურია, ლანჩხუთი"],"BirthDate":["15.06.1961"],"Relationship":["ძმის მეუღლე"],"Comment":{}}],"Properties":[{"Address":["საქართველო, ქალაქი თელავის მუნიციპალიტეტი, თბილისის ქუჩა #24"],"Area":[102],"RegistrationDetails":{},"BlockList":{},"IsRegisteredInGeorgia":{},"Share":[100],"PropertyType":["საცხოვრებელი სახლი"],"PurchaseForm":["მემკვიდრეობა"],"PurchaseDate":["01.01.1900"],"PurchaseYear":[2010],"Price":[0],"CurrencyName":["GEL"],"Details":{},"Shareholders":[],"OwnerFirstName":["ქრისტინე"],"OwnerLatsName":["თეიმურაზიშვილი"],"OwnerId":[30938],"Comment":{},"RelationName":[""]},{"Address":["საქართველო, ქალაქი თბილისი, ანა პოლიტკოვსკაიას #5, სართული 8, ბინა#56, ბლოკი2"],"Area":[77.8],"RegistrationDetails":{},"BlockList":{},"IsRegisteredInGeorgia":{},"Share":[30],"PropertyType":["ბინა"],"PurchaseForm":["ყიდვა"],"PurchaseDate":["01.01.1900"],"PurchaseYear":[2015],"Price":[21000],"CurrencyName":["GEL"],"Details":{},"Shareholders":[{"FirstName":["გიორგი"],"LastName":["თეიმურაზიშვილი"],"RelationShipName":[""],"Share":[0]}],"OwnerFirstName":["თამილა"],"OwnerLatsName":["თეიმურაზიშვილი"],"OwnerId":{},"Comment":{},"RelationName":[""]},{"Address":["საქართველო, თელავის რაიონი, სოფ. ვარდისუბანი, თელავის რაიონი, სოფ.ვარდისუბანი"],"Area":[1477.63],"RegistrationDetails":{},"BlockList":{},"IsRegisteredInGeorgia":{},"Share":[100],"PropertyType":["მიწის ნაკვეთი"],"PurchaseForm":["უსასყიდლოდ სახელწიფოს მიერ"],"PurchaseDate":["01.01.1900"],"PurchaseYear":[1999],"Price":[0],"CurrencyName":["GEL"],"Details":{},"Shareholders":[],"OwnerFirstName":["თამილა"],"OwnerLatsName":["თეიმურაზიშვილი"],"OwnerId":{},"Comment":{},"RelationName":[""]},{"Address":["საქართველო, კახეთი, თელავი, თბილისის ქ#24"],"Area":[606],"RegistrationDetails":{},"BlockList":{},"IsRegisteredInGeorgia":{},"Share":[100],"PropertyType":["მიწის ნაკვეთი"],"PurchaseForm":["მემკვიდრეობა"],"PurchaseDate":["01.01.1900"],"PurchaseYear":[2010],"Price":[0],"CurrencyName":["GEL"],"Details":{},"Shareholders":[],"OwnerFirstName":["ქრისტინე"],"OwnerLatsName":["თეიმურაზიშვილი"],"OwnerId":[30938],"Comment":{},"RelationName":[""]},{"Address":["საქართველო, კახეთი, თელავი,სოფ.ვარდისუბანი, კახეთი, თელავი, სოფ.ვარდისუბანი"],"Area":[2947],"RegistrationDetails":{},"BlockList":{},"IsRegisteredInGeorgia":{},"Share":[100],"PropertyType":["მიწის ნაკვეთი"],"PurchaseForm":["მემკვიდრეობა"],"PurchaseDate":["01.01.1900"],"PurchaseYear":[2010],"Price":[0],"CurrencyName":["GEL"],"Details":{},"Shareholders":[],"OwnerFirstName":["ქრისტინე"],"OwnerLatsName":["თეიმურაზიშვილი"],"OwnerId":[30938],"Comment":{},"RelationName":[""]}],"MovableProperties":[],"Securities":[],"BankAccounts":[{"BankName":["ლიბერთი ბანკი"],"AccountType":["ანაბარი"],"Type":[1],"Currency":["GEL"],"Amount":[5835],"OwnerFirstName":["თამილა"],"OwnerLatsName":["თეიმურაზიშვილი"],"OwnerId":{},"Comment":{},"RelationName":[""]},{"BankName":["საქართველოს ბანკი"],"AccountType":["სახელფასო"],"Type":[1],"Currency":["GEL"],"Amount":[2624],"OwnerFirstName":["თამილა"],"OwnerLatsName":["თეიმურაზიშვილი"],"OwnerId":{},"Comment":{},"RelationName":[""]},{"BankName":["საქართველოს ბანკი"],"AccountType":["ანაბარი"],"Type":[1],"Currency":["GEL"],"Amount":[840],"OwnerFirstName":["თამილა"],"OwnerLatsName":["თეიმურაზიშვილი"],"OwnerId":{},"Comment":{},"RelationName":[""]},{"BankName":["\"საქართველოს ბანკი\""],"AccountType":["სახელფასო"],"Type":[1],"Currency":["GEL"],"Amount":[1500],"OwnerFirstName":["ნინო"],"OwnerLatsName":["ჩხაიძე"],"OwnerId":[30941],"Comment":{},"RelationName":[""]},{"BankName":["\"საქართველოს ბანკი\""],"AccountType":["სახელფასო"],"Type":[1],"Currency":["GEL"],"Amount":[70],"OwnerFirstName":["ზურაბ"],"OwnerLatsName":["თეიმურაზიშვილი"],"OwnerId":[30940],"Comment":{},"RelationName":[""]}],"Cashes":[],"Jobs":[{"Organisation":["თელავის შპს 'ბავშვთა ჯანმრთელობის ცენტრი\""],"Position":["დირექტორი"],"Amount":[16560],"Currency":["GEL"],"StartDate":["01.01.2017"],"EndDate":["31.12.2017"],"IsSecret":[false],"OwnerFirstName":["თამილა"],"OwnerLatsName":["თეიმურაზიშვილი"],"OwnerId":{},"Comment":{},"RelationName":[""]},{"Organisation":["თელავის შპს \"ბავშვთა ჯანმრთელობის ცენტრი\" რებილიტაციური განყოფილება"],"Position":["სოციალური რეაბილიტაციის და ბავშვზე ზრუნვის სახელმწიფო პროგრამის ბავშვთა რეაბილიტაციის ქვეპროგრამის კოორდინატორი"],"Amount":[7010],"Currency":["GEL"],"StartDate":["01.01.2017"],"EndDate":["31.12.2017"],"IsSecret":[false],"OwnerFirstName":["თამილა"],"OwnerLatsName":["თეიმურაზიშვილი"],"OwnerId":{},"Comment":{},"RelationName":[""]},{"Organisation":["თელავის შპს \"ბავშვთა ჯანმრთელობის ცენტრი\" პოლიკლინიკური განყოფილება"],"Position":["ოჯახის ექიმი-პედიატრი"],"Amount":[10037],"Currency":["GEL"],"StartDate":["01.01.2017"],"EndDate":["31.12.2017"],"IsSecret":[false],"OwnerFirstName":["ნინო"],"OwnerLatsName":["ჩხაიძე"],"OwnerId":[30941],"Comment":{},"RelationName":[""]},{"Organisation":["სოციალური მომსახურების სააგენტო, კახეთის სამხარეო ცენტრი"],"Position":["შტატგარეშე თანამშრომელი"],"Amount":[7680],"Currency":["GEL"],"StartDate":["01.01.2017"],"EndDate":["31.12.2017"],"IsSecret":[false],"OwnerFirstName":["ნინო"],"OwnerLatsName":["ჩხაიძე"],"OwnerId":[30941],"Comment":{},"RelationName":[""]},{"Organisation":["შპს საქართველოს გაერთიანებული წყალმომარაგების კომპანია"],"Position":["ჩქარი ფილტრების მორიგე ოპერატორი"],"Amount":[4440],"Currency":["GEL"],"StartDate":["01.01.2017"],"EndDate":["31.12.2017"],"IsSecret":[false],"OwnerFirstName":["ზურაბ"],"OwnerLatsName":["თეიმურაზიშვილი"],"OwnerId":[30940],"Comment":{},"RelationName":[""]},{"Organisation":["აიპ სპორტულ კლუბთა გაერთიანება თელავი"],"Position":["საჭადრაკო კლუბის მენეჯერი"],"Amount":[3775],"Currency":["GEL"],"StartDate":["01.01.2017"],"EndDate":["31.12.2017"],"IsSecret":[false],"OwnerFirstName":["ზურაბ"],"OwnerLatsName":["თეიმურაზიშვილი"],"OwnerId":[30940],"Comment":{},"RelationName":[""]}],"Contracts":[{"ContractType":["სესხი"],"Subject":["ბინის რემონტი"],"Amount":[8120],"AmountCurrency":{},"Currency":["GEL"],"StartDate":["14.06.2016"],"EffectiveDate":["14.06.2016"],"EndDate":["03.06.2019"],"EndDateName":["03.06.2019"],"Agency":["საქართველოს ბანკი"],"Type":[2],"Income":[3440.76],"IncomeCurrency":["GEL"],"OwnerFirstName":["ნინო"],"OwnerLatsName":["ჩხაიძე"],"OwnerId":[30941],"Comment":{},"RelationName":[""]}],"Gifts":[],"InOuts":[],"Enterprice":[],"LinkedEnterprice":[],"DeclarationHistory":{}},{"Id":[33113],"FirstName":["თამილა"],"LastName":["თეიმურაზიშვილი"],"Organisation":["შპს-ბავშვთა ჯანმრთელობის ცენტრი"],"Position":["ხელმძღვანელი"],"BirthPlace":["საქართველო, ქალაქი თელავი"],"BirthDate":["13.08.1953"],"VersionId":{},"DateEdited":{},"DeclarationSubmitDate":["31.03.2017"],"FamilyMembers":[{"FirstName":["ქრისტინე"],"LastName":["თეიმურაზიშვილი"],"BirthPlace":["საქართველო, კახეთი, თელავი, სოფ.სანიორე"],"BirthDate":["22.12.1927"],"Relationship":["დედა"],"Comment":{}},{"FirstName":["სოლომონ"],"LastName":["თეიმურაზიშვილი"],"BirthPlace":["საქართველო, კახეთი, თელავი"],"BirthDate":["03.09.1950"],"Relationship":["ძმა"],"Comment":{}},{"FirstName":["ზურაბ"],"LastName":["თეიმურაზიშვილი"],"BirthPlace":["საქართველო, კახეთი, თელავი"],"BirthDate":["31.07.1961"],"Relationship":["ძმა"],"Comment":{}},{"FirstName":["ნინო"],"LastName":["ჩხაიძე"],"BirthPlace":["საქართველო, გურია, ლანჩხუთი"],"BirthDate":["15.06.1961"],"Relationship":["ძმის მეუღლე"],"Comment":{}}],"Properties":[{"Address":["საქართველო, ქალაქი თელავის მუნიციპალიტეტი, თბილისის ქუჩა #24"],"Area":[102],"RegistrationDetails":{},"BlockList":{},"IsRegisteredInGeorgia":{},"Share":[100],"PropertyType":["საცხოვრებელი სახლი"],"PurchaseForm":["მემკვიდრეობა"],"PurchaseDate":["01.01.1900"],"PurchaseYear":{},"Price":[0],"CurrencyName":["GEL"],"Details":{},"Shareholders":[],"OwnerFirstName":["ქრისტინე"],"OwnerLatsName":["თეიმურაზიშვილი"],"OwnerId":[30938],"Comment":{},"RelationName":[""]},{"Address":["საქართველო, ქალაქი თბილისი, ანა პოლიტკოვსკაიას #5, სართული 8, ბინა#56, ბლოკი2"],"Area":[77.8],"RegistrationDetails":{},"BlockList":{},"IsRegisteredInGeorgia":{},"Share":[30],"PropertyType":["ბინა"],"PurchaseForm":["ყიდვა"],"PurchaseDate":["01.01.1900"],"PurchaseYear":{},"Price":[21000],"CurrencyName":["GEL"],"Details":{},"Shareholders":[{"FirstName":["გიორგი"],"LastName":["თეიმურაზიშვილი"],"RelationShipName":[""],"Share":[0]}],"OwnerFirstName":["თამილა"],"OwnerLatsName":["თეიმურაზიშვილი"],"OwnerId":{},"Comment":{},"RelationName":[""]},{"Address":["საქართველო, თელავის რაიონი, სოფ. ვარდისუბანი, თელავის რაიონი, სოფ.ვარდისუბანი"],"Area":[1477.63],"RegistrationDetails":{},"BlockList":{},"IsRegisteredInGeorgia":{},"Share":[100],"PropertyType":["მიწის ნაკვეთი"],"PurchaseForm":["უსასყიდლოდ სახელწიფოს მიერ"],"PurchaseDate":["01.01.1900"],"PurchaseYear":{},"Price":[0],"CurrencyName":["GEL"],"Details":{},"Shareholders":[],"OwnerFirstName":["თამილა"],"OwnerLatsName":["თეიმურაზიშვილი"],"OwnerId":{},"Comment":{},"RelationName":[""]},{"Address":["საქართველო, კახეთი, თელავი, თბილისის ქ#24"],"Area":[606],"RegistrationDetails":{},"BlockList":{},"IsRegisteredInGeorgia":{},"Share":[100],"PropertyType":["მიწის ნაკვეთი"],"PurchaseForm":["მემკვიდრეობა"],"PurchaseDate":["01.01.1900"],"PurchaseYear":{},"Price":[0],"CurrencyName":["GEL"],"Details":{},"Shareholders":[],"OwnerFirstName":["ქრისტინე"],"OwnerLatsName":["თეიმურაზიშვილი"],"OwnerId":[30938],"Comment":{},"RelationName":[""]},{"Address":["საქართველო, კახეთი, თელავი,სოფ.ვარდისუბანი, კახეთი, თელავი, სოფ.ვარდისუბანი"],"Area":[2947],"RegistrationDetails":{},"BlockList":{},"IsRegisteredInGeorgia":{},"Share":[100],"PropertyType":["მიწის ნაკვეთი"],"PurchaseForm":["მემკვიდრეობა"],"PurchaseDate":["01.01.1900"],"PurchaseYear":{},"Price":[0],"CurrencyName":["GEL"],"Details":{},"Shareholders":[],"OwnerFirstName":["ქრისტინე"],"OwnerLatsName":["თეიმურაზიშვილი"],"OwnerId":[30938],"Comment":{},"RelationName":[""]}],"MovableProperties":[],"Securities":[],"BankAccounts":[{"BankName":["ლიბერთი ბანკი"],"AccountType":["ანაბარი"],"Type":[1],"Currency":["GEL"],"Amount":[5128],"OwnerFirstName":["თამილა"],"OwnerLatsName":["თეიმურაზიშვილი"],"OwnerId":{},"Comment":{},"RelationName":[""]},{"BankName":["საქართველოს ბანკი"],"AccountType":["სახელფასო"],"Type":[1],"Currency":["GEL"],"Amount":[3128],"OwnerFirstName":["თამილა"],"OwnerLatsName":["თეიმურაზიშვილი"],"OwnerId":{},"Comment":{},"RelationName":[""]},{"BankName":["საქართველოს ბანკი"],"AccountType":["ანაბარი"],"Type":[1],"Currency":["GEL"],"Amount":[300],"OwnerFirstName":["თამილა"],"OwnerLatsName":["თეიმურაზიშვილი"],"OwnerId":{},"Comment":{},"RelationName":[""]},{"BankName":["\"საქართველოს ბანკი\""],"AccountType":["სახელფასო"],"Type":[1],"Currency":["GEL"],"Amount":[520],"OwnerFirstName":["ნინო"],"OwnerLatsName":["ჩხაიძე"],"OwnerId":[30941],"Comment":{},"RelationName":[""]},{"BankName":["\"საქართველოს ბანკი\""],"AccountType":["სახელფასო"],"Type":[1],"Currency":["GEL"],"Amount":[0],"OwnerFirstName":["ზურაბ"],"OwnerLatsName":["თეიმურაზიშვილი"],"OwnerId":[30940],"Comment":{},"RelationName":[""]}],"Cashes":[],"Jobs":[{"Organisation":["თელავის შპს 'ბავშვთა ჯანმრთელობის ცენტრი\""],"Position":["დირექტორი"],"Amount":[17400],"Currency":["GEL"],"StartDate":["01.01.2016"],"EndDate":["31.12.2016"],"IsSecret":[false],"OwnerFirstName":["თამილა"],"OwnerLatsName":["თეიმურაზიშვილი"],"OwnerId":{},"Comment":{},"RelationName":[""]},{"Organisation":["თელავის შპს \"ბავშვთა ჯანმრთელობის ცენტრი\" რებილიტაციური განყოფილება"],"Position":["სოციალური რეაბილიტაციის და ბავშვზე ზრუნვის სახელმწიფო პროგრამის ბავშვთა რეაბილიტაციის ქვეპროგრამის კოორდინატორი"],"Amount":[7040],"Currency":["GEL"],"StartDate":["01.01.2016"],"EndDate":["31.12.2016"],"IsSecret":[false],"OwnerFirstName":["თამილა"],"OwnerLatsName":["თეიმურაზიშვილი"],"OwnerId":{},"Comment":{},"RelationName":[""]},{"Organisation":["თელავის შპს \"ბავშვთა ჯანმრთელობის ცენტრი\" პოლიკლინიკური განყოფილება"],"Position":["ოჯახის ექიმი-პედიატრი"],"Amount":[7374.5],"Currency":["GEL"],"StartDate":["01.01.2016"],"EndDate":["31.12.2016"],"IsSecret":[false],"OwnerFirstName":["ნინო"],"OwnerLatsName":["ჩხაიძე"],"OwnerId":[30941],"Comment":{},"RelationName":[""]},{"Organisation":["სოციალური მომსახურების სააგენტო, კახეთის სამხარეო ცენტრი"],"Position":["შტატგარეშე თანამშრომელი"],"Amount":[7680],"Currency":["GEL"],"StartDate":["01.01.2016"],"EndDate":["31.12.2016"],"IsSecret":[false],"OwnerFirstName":["ნინო"],"OwnerLatsName":["ჩხაიძე"],"OwnerId":[30941],"Comment":{},"RelationName":[""]},{"Organisation":["შპს საქართველოს გაერთიანებული წყალმომარაგების კომპანია"],"Position":["ჩქარი ფილტრების მორიგე ოპერატორი"],"Amount":[4440],"Currency":["GEL"],"StartDate":["01.01.2016"],"EndDate":["31.12.2016"],"IsSecret":[false],"OwnerFirstName":["ზურაბ"],"OwnerLatsName":["თეიმურაზიშვილი"],"OwnerId":[30940],"Comment":{},"RelationName":[""]},{"Organisation":["აიპ სპორტულ კლუბთა გაერთიანება თელავი"],"Position":["საქმეთა მწარმოებელი"],"Amount":[1312],"Currency":["GEL"],"StartDate":["01.10.2016"],"EndDate":["31.12.2016"],"IsSecret":[false],"OwnerFirstName":["ზურაბ"],"OwnerLatsName":["თეიმურაზიშვილი"],"OwnerId":[30940],"Comment":{},"RelationName":[""]}],"Contracts":[{"ContractType":["სესხი"],"Subject":["ბინის რემონტი"],"Amount":[8120],"AmountCurrency":{},"Currency":["GEL"],"StartDate":["14.06.2016"],"EffectiveDate":["14.06.2016"],"EndDate":["03.06.2019"],"EndDateName":["03.06.2019"],"Agency":["საქართველოს ბანკი"],"Type":[2],"Income":[1782.03],"IncomeCurrency":["GEL"],"OwnerFirstName":["ნინო"],"OwnerLatsName":["ჩხაიძე"],"OwnerId":[30941],"Comment":{},"RelationName":[""]}],"Gifts":[],"InOuts":[],"Enterprice":[],"LinkedEnterprice":[],"DeclarationHistory":{}},{"Id":[959829],"FirstName":["თამილა"],"LastName":["თეიმურაზიშვილი"],"Organisation":["შპს-ბავშვთა ჯანმრთელობის ცენტრი"],"Position":["ხელმძღვანელი"],"BirthPlace":["საქართველო, ქალაქი თელავი"],"BirthDate":["13.08.1953"],"VersionId":{},"DateEdited":{},"DeclarationSubmitDate":["30.03.2016"],"FamilyMembers":[{"FirstName":["ქრისტინე"],"LastName":["თეიმურაზიშვილი"],"BirthPlace":["საქართველო, კახეთი, თელავი, სოფ.სანიორე, "],"BirthDate":["22.12.1927"],"Relationship":["დედა"],"Comment":{}},{"FirstName":["სოლომონ"],"LastName":["თეიმურაზიშვილი"],"BirthPlace":["საქართველო, კახეთი, თელავი, "],"BirthDate":["03.09.1950"],"Relationship":["ძმა"],"Comment":{}},{"FirstName":["ზურაბ"],"LastName":["თეიმურაზიშვილი"],"BirthPlace":["საქართველო, კახეთი, თელავი, "],"BirthDate":["31.07.1961"],"Relationship":["ძმა"],"Comment":{}},{"FirstName":["ნინო"],"LastName":["ჩხაიძე"],"BirthPlace":["საქართველო, გურია, ლანჩხუთი, "],"BirthDate":["15.06.1961"],"Relationship":["ძმის მეუღლე"],"Comment":{}}],"Properties":[{"Address":["საქართველო, ქალაქი თბილისი, ანა პოლიტკოვსკაიას #5, სართული 8, ბინა#56, ბლოკი2"],"Area":[77.8],"RegistrationDetails":{},"BlockList":{},"IsRegisteredInGeorgia":{},"Share":[30],"PropertyType":["ბინა"],"PurchaseForm":[""],"PurchaseDate":[""],"PurchaseYear":{},"Price":[0],"CurrencyName":["GEL"],"Details":{},"Shareholders":[{"FirstName":["გიორგი"],"LastName":["თეიმურაზიშვილი"],"RelationShipName":[""],"Share":[0]}],"OwnerFirstName":["თამილა"],"OwnerLatsName":["თეიმურაზიშვილი"],"OwnerId":{},"Comment":{},"RelationName":["()"]},{"Address":["საქართველო, თელავის რაიონი, სოფ. ვარდისუბანი, "],"Area":[1477.63],"RegistrationDetails":{},"BlockList":{},"IsRegisteredInGeorgia":{},"Share":[100],"PropertyType":["მიწის ნაკვეთი"],"PurchaseForm":[""],"PurchaseDate":[""],"PurchaseYear":{},"Price":[0],"CurrencyName":["GEL"],"Details":{},"Shareholders":[],"OwnerFirstName":["თამილა"],"OwnerLatsName":["თეიმურაზიშვილი"],"OwnerId":{},"Comment":{},"RelationName":["()"]},{"Address":["საქართველო, კახეთი, თელავი, თბილისის ქ#24"],"Area":[102],"RegistrationDetails":{},"BlockList":{},"IsRegisteredInGeorgia":{},"Share":[100],"PropertyType":["საცხოვრებელი სახლი"],"PurchaseForm":[""],"PurchaseDate":[""],"PurchaseYear":{},"Price":[0],"CurrencyName":["GEL"],"Details":{},"Shareholders":[],"OwnerFirstName":["ქრისტინე"],"OwnerLatsName":["თეიმურაზიშვილი"],"OwnerId":[990438],"Comment":{},"RelationName":[""]},{"Address":["საქართველო, კახეთი, თელავი, თბილისის ქ#24"],"Area":[606],"RegistrationDetails":{},"BlockList":{},"IsRegisteredInGeorgia":{},"Share":[100],"PropertyType":["მიწის ნაკვეთი"],"PurchaseForm":[""],"PurchaseDate":[""],"PurchaseYear":{},"Price":[0],"CurrencyName":["GEL"],"Details":{},"Shareholders":[],"OwnerFirstName":["ქრისტინე"],"OwnerLatsName":["თეიმურაზიშვილი"],"OwnerId":[990438],"Comment":{},"RelationName":[""]},{"Address":["საქართველო, კახეთი, თელავი,სოფ.ვარდისუბანი, "],"Area":[2947],"RegistrationDetails":{},"BlockList":{},"IsRegisteredInGeorgia":{},"Share":[100],"PropertyType":["მიწის ნაკვეთი"],"PurchaseForm":[""],"PurchaseDate":[""],"PurchaseYear":{},"Price":[0],"CurrencyName":["GEL"],"Details":{},"Shareholders":[],"OwnerFirstName":["ქრისტინე"],"OwnerLatsName":["თეიმურაზიშვილი"],"OwnerId":[990438],"Comment":{},"RelationName":[""]}],"MovableProperties":[],"Securities":[],"BankAccounts":[{"BankName":["ლიბერთი ბანკი"],"AccountType":["სახელფასო"],"Type":[1],"Currency":["GEL"],"Amount":[5320],"OwnerFirstName":["თამილა"],"OwnerLatsName":["თეიმურაზიშვილი"],"OwnerId":[1016129],"Comment":{},"RelationName":["()"]},{"BankName":["ლიბერთი ბანკი"],"AccountType":["მიმდინარე"],"Type":[1],"Currency":["GEL"],"Amount":[656],"OwnerFirstName":["თამილა"],"OwnerLatsName":["თეიმურაზიშვილი"],"OwnerId":[1016129],"Comment":{},"RelationName":["()"]},{"BankName":["ლიბერთი ბანკი"],"AccountType":["სახელფასო"],"Type":[1],"Currency":["GEL"],"Amount":[903],"OwnerFirstName":["ნინო"],"OwnerLatsName":["ჩხაიძე"],"OwnerId":[1016133],"Comment":{},"RelationName":[""]},{"BankName":["საქართველოს ბანკი"],"AccountType":["სახელფასო"],"Type":[1],"Currency":["GEL"],"Amount":[43],"OwnerFirstName":["თამილა"],"OwnerLatsName":["თეიმურაზიშვილი"],"OwnerId":[1016129],"Comment":{},"RelationName":["()"]},{"BankName":["საქართველოს ბანკი"],"AccountType":["ანაბარი"],"Type":[1],"Currency":["GEL"],"Amount":[50],"OwnerFirstName":["თამილა"],"OwnerLatsName":["თეიმურაზიშვილი"],"OwnerId":[1016129],"Comment":{},"RelationName":["()"]}],"Cashes":[],"Jobs":[{"Organisation":["შპს-ბავშვთა ჯანმრთელობის ცენტრი"],"Position":["შპს-ბავშვთა ჯანმრთელობის ცენტრი"],"Amount":[6500],"Currency":["GEL"],"StartDate":[""],"EndDate":[""],"IsSecret":[false],"OwnerFirstName":["თამილა"],"OwnerLatsName":["თეიმურაზიშვილი"],"OwnerId":[1016129],"Comment":{},"RelationName":["()"]},{"Organisation":["შპს თელავის ბავშვთა ჯანმრთელობის ცენტრი"],"Position":["შპს თელავის ბავშვთა ჯანმრთელობის ცენტრი"],"Amount":[3600],"Currency":["GEL"],"StartDate":[""],"EndDate":[""],"IsSecret":[false],"OwnerFirstName":["ნინო"],"OwnerLatsName":["ჩხაიძე"],"OwnerId":[1016133],"Comment":{},"RelationName":[""]},{"Organisation":["სოციიალური მომსახურების სააგენტო, კახეთის სამხარეო ცენტრი"],"Position":["სოციიალური მომსახურების სააგენტო, კახეთის სამხარეო ცენტრი"],"Amount":[4500],"Currency":["GEL"],"StartDate":[""],"EndDate":[""],"IsSecret":[false],"OwnerFirstName":["ნინო"],"OwnerLatsName":["ჩხაიძე"],"OwnerId":[1016133],"Comment":{},"RelationName":[""]},{"Organisation":["შპს-საქართველოს გაერთიანებული წყალმომარაგების კომპანია"],"Position":["შპს-საქართველოს გაერთიანებული წყალმომარაგების კომპანია"],"Amount":[3460],"Currency":["GEL"],"StartDate":[""],"EndDate":[""],"IsSecret":[false],"OwnerFirstName":["ზურაბ"],"OwnerLatsName":["თეიმურაზიშვილი"],"OwnerId":[990440],"Comment":{},"RelationName":[""]}],"Contracts":[{"ContractType":["ნასყიდობა"],"Subject":["მშენებარე საცხოვრებელი ბინის 30 %-ის შეძენა. ქალაქი თბილისი  ანა პოლიტკოვსკაიას ქ#5, სართული 8, ბინა#56, ბლოკი 2"],"Amount":[21000],"AmountCurrency":{},"Currency":["USD"],"StartDate":["05.01.2015"],"EffectiveDate":["14.01.2015"],"EndDate":["31.12.2015"],"EndDateName":{},"Agency":["სსიპ საჯარო რეესტრის თბილისის ფილიალი"],"Type":[2],"Income":[21000],"IncomeCurrency":["USD"],"OwnerFirstName":["თამილა"],"OwnerLatsName":["თეიმურაზიშვილი"],"OwnerId":{},"Comment":{},"RelationName":["()"]},{"ContractType":["სესხი"],"Subject":["ბინის რემონტი"],"Amount":[3500],"AmountCurrency":{},"Currency":["GEL"],"StartDate":["08.07.2014"],"EffectiveDate":["08.07.2014"],"EndDate":["04.01.2016"],"EndDateName":{},"Agency":["ლიბერთი ბანკის თელავის ფილიალი"],"Type":[2],"Income":[2580],"IncomeCurrency":["GEL"],"OwnerFirstName":["თამილა"],"OwnerLatsName":["თეიმურაზიშვილი"],"OwnerId":{},"Comment":{},"RelationName":["()"]}],"Gifts":[],"InOuts":[],"Enterprice":[{"LegalFormName":{},"Name":["შპს ბავშვთა ჯანმრთელობის ცენტრი"],"EnterpriseCountry":{},"EnterpriseCity":{},"EnterpriseAddress":["ალ. ალადაშვილის ქ #2"],"PartnershipForm":{},"StartDate":["16.03.2000"],"EndDateType":[0],"EndDate":[""],"EndDateName":["უვადო"],"RegistrationAgency":["თელავის რაიონის სასამართლო"],"RegisterDate":["16.03.2000"],"Share":[0],"Income":[13300],"IncomeCurrencyName":["GEL"],"AbbreviationName":{},"AbbreviationTypeId":{},"CapitalAmount":{},"CapitalAmoutCurrencyName":{},"OtherAbbreviationName":{},"PartnershipFormName":["დირექტორი"],"EnterprisePartners":[],"LinkedEnterprises":[],"OwnerFirstName":{},"OwnerLatsName":{},"OwnerId":{},"Comment":{},"RelationName":{}}],"LinkedEnterprice":[],"DeclarationHistory":{}},{"Id":[952901],"FirstName":["თამილა"],"LastName":["თეიმურაზიშვილი"],"Organisation":["შპს-ბავშვთა ჯანმრთელობის ცენტრი"],"Position":["ხელმძღვანელი"],"BirthPlace":["საქართველო, ქალაქი თელავი"],"BirthDate":["13.08.1953"],"VersionId":{},"DateEdited":{},"DeclarationSubmitDate":["23.03.2015"],"FamilyMembers":[{"FirstName":["ქრისტინე"],"LastName":["თეიმურაზიშვილი"],"BirthPlace":["საქართველო, კახეთი, თელავი, სოფ.სანიორე, "],"BirthDate":["22.12.1927"],"Relationship":["დედა"],"Comment":{}},{"FirstName":["სოლომონ"],"LastName":["თეიმურაზიშვილი"],"BirthPlace":["საქართველო, კახეთი, თელავი, "],"BirthDate":["03.09.1950"],"Relationship":["ძმა"],"Comment":{}},{"FirstName":["ზურაბ"],"LastName":["თეიმურაზიშვილი"],"BirthPlace":["საქართველო, კახეთი, თელავი, "],"BirthDate":["31.07.1961"],"Relationship":["ძმა"],"Comment":{}},{"FirstName":["ნინო"],"LastName":["ჩხაიძე"],"BirthPlace":["საქართველო, გურია, ლანჩხუთი, "],"BirthDate":["15.06.1961"],"Relationship":["ძმის მეუღლე"],"Comment":{}}],"Properties":[{"Address":["საქართველო, ქალაქი თბილისი, ანა პოლიტკოვსკაიას #5, სართული 8, ბინა#56, ბლოკი2"],"Area":[77.8],"RegistrationDetails":{},"BlockList":{},"IsRegisteredInGeorgia":{},"Share":[30],"PropertyType":["ბინა"],"PurchaseForm":[""],"PurchaseDate":[""],"PurchaseYear":{},"Price":[0],"CurrencyName":["GEL"],"Details":{},"Shareholders":[{"FirstName":["გიორგი"],"LastName":["თეიმურაზიშვილი"],"RelationShipName":[""],"Share":[0]}],"OwnerFirstName":["თამილა"],"OwnerLatsName":["თეიმურაზიშვილი"],"OwnerId":[982371],"Comment":{},"RelationName":["()"]},{"Address":["საქართველო, თელავის რაიონი, სოფ. ვარდისუბანი, "],"Area":[1477.63],"RegistrationDetails":{},"BlockList":{},"IsRegisteredInGeorgia":{},"Share":[100],"PropertyType":["მიწის ნაკვეთი"],"PurchaseForm":[""],"PurchaseDate":[""],"PurchaseYear":{},"Price":[0],"CurrencyName":["GEL"],"Details":{},"Shareholders":[],"OwnerFirstName":["თამილა"],"OwnerLatsName":["თეიმურაზიშვილი"],"OwnerId":[954056],"Comment":{},"RelationName":["()"]},{"Address":["საქართველო, კახეთი, თელავი, თბილისის ქ#24"],"Area":[102],"RegistrationDetails":{},"BlockList":{},"IsRegisteredInGeorgia":{},"Share":[100],"PropertyType":["საცხოვრებელი სახლი"],"PurchaseForm":[""],"PurchaseDate":[""],"PurchaseYear":{},"Price":[0],"CurrencyName":["GEL"],"Details":{},"Shareholders":[],"OwnerFirstName":["ქრისტინე"],"OwnerLatsName":["თეიმურაზიშვილი"],"OwnerId":[990438],"Comment":{},"RelationName":[""]},{"Address":["საქართველო, კახეთი, თელავი, თბილისის ქ#24"],"Area":[606],"RegistrationDetails":{},"BlockList":{},"IsRegisteredInGeorgia":{},"Share":[100],"PropertyType":["მიწის ნაკვეთი"],"PurchaseForm":[""],"PurchaseDate":[""],"PurchaseYear":{},"Price":[0],"CurrencyName":["GEL"],"Details":{},"Shareholders":[],"OwnerFirstName":["ქრისტინე"],"OwnerLatsName":["თეიმურაზიშვილი"],"OwnerId":[990438],"Comment":{},"RelationName":[""]},{"Address":["საქართველო, კახეთი, თელავი,სოფ.ვარდისუბანი, "],"Area":[2947],"RegistrationDetails":{},"BlockList":{},"IsRegisteredInGeorgia":{},"Share":[100],"PropertyType":["მიწის ნაკვეთი"],"PurchaseForm":[""],"PurchaseDate":[""],"PurchaseYear":{},"Price":[0],"CurrencyName":["GEL"],"Details":{},"Shareholders":[],"OwnerFirstName":["ქრისტინე"],"OwnerLatsName":["თეიმურაზიშვილი"],"OwnerId":[990438],"Comment":{},"RelationName":[""]}],"MovableProperties":[],"Securities":[],"BankAccounts":[{"BankName":["ლიბერთი ბანკი"],"AccountType":["სახელფასო"],"Type":[1],"Currency":["GEL"],"Amount":[811],"OwnerFirstName":["თამილა"],"OwnerLatsName":["თეიმურაზიშვილი"],"OwnerId":[982371],"Comment":{},"RelationName":["()"]},{"BankName":["ლიბერთი ბანკი"],"AccountType":["მიმდინარე"],"Type":[1],"Currency":["GEL"],"Amount":[657],"OwnerFirstName":["თამილა"],"OwnerLatsName":["თეიმურაზიშვილი"],"OwnerId":[982371],"Comment":{},"RelationName":["()"]},{"BankName":["ლიბერთი ბანკი"],"AccountType":["სახელფასო"],"Type":[1],"Currency":["GEL"],"Amount":[240],"OwnerFirstName":["ნინო"],"OwnerLatsName":["ჩხაიძე"],"OwnerId":[990441],"Comment":{},"RelationName":[""]}],"Cashes":[],"Jobs":[{"Organisation":["შპს-ბავშვთა ჯანმრთელობის ცენტრი"],"Position":["შპს-ბავშვთა ჯანმრთელობის ცენტრი"],"Amount":[4173],"Currency":["GEL"],"StartDate":[""],"EndDate":[""],"IsSecret":[false],"OwnerFirstName":["თამილა"],"OwnerLatsName":["თეიმურაზიშვილი"],"OwnerId":[982371],"Comment":{},"RelationName":["()"]},{"Organisation":["შპს თელავის ბავშვთა ჯანმრთელობის ცენტრი"],"Position":["შპს თელავის ბავშვთა ჯანმრთელობის ცენტრი"],"Amount":[3562],"Currency":["GEL"],"StartDate":[""],"EndDate":[""],"IsSecret":[false],"OwnerFirstName":["ნინო"],"OwnerLatsName":["ჩხაიძე"],"OwnerId":[990441],"Comment":{},"RelationName":[""]},{"Organisation":["სოციიალური მომსახურების სააგენტო, კახეთის სამხარეო ცენტრი"],"Position":["სოციიალური მომსახურების სააგენტო, კახეთის სამხარეო ცენტრი"],"Amount":[4340],"Currency":["GEL"],"StartDate":[""],"EndDate":[""],"IsSecret":[false],"OwnerFirstName":["ნინო"],"OwnerLatsName":["ჩხაიძე"],"OwnerId":[990441],"Comment":{},"RelationName":[""]},{"Organisation":["შპს-საქართველოს გაერთიანებული წყალმომარაგების კომპანია"],"Position":["შპს-საქართველოს გაერთიანებული წყალმომარაგების კომპანია"],"Amount":[3460],"Currency":["GEL"],"StartDate":[""],"EndDate":[""],"IsSecret":[false],"OwnerFirstName":["ზურაბ"],"OwnerLatsName":["თეიმურაზიშვილი"],"OwnerId":[990440],"Comment":{},"RelationName":[""]}],"Contracts":[{"ContractType":["ნასყიდობა"],"Subject":["საცხოვრებელი ბინის გაყიდვა.ქალაქი თელავი , კავკასიონის 45ა"],"Amount":[21000],"AmountCurrency":{},"Currency":["USD"],"StartDate":["10.06.2014"],"EffectiveDate":["13.06.2014"],"EndDate":["13.06.2014"],"EndDateName":{},"Agency":["სსიპ საჯარო რეესტრი თელავის ფილიალი"],"Type":[1],"Income":[21000],"IncomeCurrency":["USD"],"OwnerFirstName":["თამილა"],"OwnerLatsName":["თეიმურაზიშვილი"],"OwnerId":[982371],"Comment":{},"RelationName":["()"]},{"ContractType":["ნასყიდობა"],"Subject":["მშენებარე საცხოვრებელი ბინის 30 %-ის შეძენა. ქალაქი თბილისი  ანა პოლიტკოვსკაიას ქ#5, სართული 8, ბინა#56, ბლოკი 2"],"Amount":[21000],"AmountCurrency":{},"Currency":["USD"],"StartDate":["05.01.2015"],"EffectiveDate":["14.01.2015"],"EndDate":["31.12.2015"],"EndDateName":{},"Agency":["სსიპ საჯარო რეესტრის თბილისის ფილიალი"],"Type":[2],"Income":[0],"IncomeCurrency":["USD"],"OwnerFirstName":["თამილა"],"OwnerLatsName":["თეიმურაზიშვილი"],"OwnerId":[982371],"Comment":{},"RelationName":["()"]},{"ContractType":["სესხი"],"Subject":["ბინის რემონტი"],"Amount":[3500],"AmountCurrency":{},"Currency":["GEL"],"StartDate":["08.07.2014"],"EffectiveDate":["08.07.2014"],"EndDate":["04.01.2016"],"EndDateName":{},"Agency":["ლიბერთი ბანკის თელავის ფილიალი"],"Type":[2],"Income":[1075.35],"IncomeCurrency":["GEL"],"OwnerFirstName":["თამილა"],"OwnerLatsName":["თეიმურაზიშვილი"],"OwnerId":[982371],"Comment":{},"RelationName":["()"]}],"Gifts":[],"InOuts":[],"Enterprice":[{"LegalFormName":{},"Name":["შპს ბავშვთა ჯანმრთელობის ცენტრი"],"EnterpriseCountry":{},"EnterpriseCity":{},"EnterpriseAddress":["ალ. ალადაშვილის ქ #2"],"PartnershipForm":{},"StartDate":["16.03.2000"],"EndDateType":[0],"EndDate":[""],"EndDateName":["უვადო"],"RegistrationAgency":["თელავის რაიონის სასამართლო"],"RegisterDate":["16.03.2000"],"Share":[0],"Income":[7800],"IncomeCurrencyName":["GEL"],"AbbreviationName":{},"AbbreviationTypeId":{},"CapitalAmount":{},"CapitalAmoutCurrencyName":{},"OtherAbbreviationName":{},"PartnershipFormName":["დირექტორი"],"EnterprisePartners":[],"LinkedEnterprises":[],"OwnerFirstName":{},"OwnerLatsName":{},"OwnerId":[982371],"Comment":{},"RelationName":{}}],"LinkedEnterprice":[],"DeclarationHistory":{}},{"Id":[946849],"FirstName":["თამილა"],"LastName":["თეიმურაზიშვილი"],"Organisation":["შპს-ბავშვთა ჯანმრთელობის ცენტრი"],"Position":["ხელმძღვანელი"],"BirthPlace":["საქართველო, ქალაქი თელავი"],"BirthDate":["13.08.1953"],"VersionId":{},"DateEdited":{},"DeclarationSubmitDate":["14.03.2014"],"FamilyMembers":[],"Properties":[{"Address":["საქართველო, ქალაქი თელავი, კავკასიონის ქ #45ა"],"Area":[69.5],"RegistrationDetails":{},"BlockList":{},"IsRegisteredInGeorgia":{},"Share":[100],"PropertyType":["ბინა"],"PurchaseForm":[""],"PurchaseDate":[""],"PurchaseYear":{},"Price":[0],"CurrencyName":["GEL"],"Details":{},"Shareholders":[],"OwnerFirstName":["თამილა"],"OwnerLatsName":["თეიმურაზიშვილი"],"OwnerId":[954056],"Comment":{},"RelationName":["()"]},{"Address":["საქართველო, თელავის რაიონი, სოფ. ვარდისუბანი, "],"Area":[1477.63],"RegistrationDetails":{},"BlockList":{},"IsRegisteredInGeorgia":{},"Share":[100],"PropertyType":["მიწის ნაკვეთი"],"PurchaseForm":[""],"PurchaseDate":[""],"PurchaseYear":{},"Price":[0],"CurrencyName":["GEL"],"Details":{},"Shareholders":[],"OwnerFirstName":["თამილა"],"OwnerLatsName":["თეიმურაზიშვილი"],"OwnerId":[954056],"Comment":{},"RelationName":["()"]}],"MovableProperties":[],"Securities":[],"BankAccounts":[{"BankName":["ლიბერთი ბანკი"],"AccountType":["სახელფასო"],"Type":[1],"Currency":["GEL"],"Amount":[692.71],"OwnerFirstName":["თამილა"],"OwnerLatsName":["თეიმურაზიშვილი"],"OwnerId":[954056],"Comment":{},"RelationName":["()"]},{"BankName":["ლიბერთი ბანკი"],"AccountType":["მიმდინარე"],"Type":[1],"Currency":["GEL"],"Amount":[560],"OwnerFirstName":["თამილა"],"OwnerLatsName":["თეიმურაზიშვილი"],"OwnerId":[954056],"Comment":{},"RelationName":["()"]}],"Cashes":[],"Jobs":[{"Organisation":["შპს-ბავშვთა ჯანმრთელობის ცენტრი"],"Position":["შპს-ბავშვთა ჯანმრთელობის ცენტრი"],"Amount":[2969],"Currency":["GEL"],"StartDate":[""],"EndDate":[""],"IsSecret":[false],"OwnerFirstName":["თამილა"],"OwnerLatsName":["თეიმურაზიშვილი"],"OwnerId":[954056],"Comment":{},"RelationName":["()"]}],"Contracts":[],"Gifts":[{"Type":["ფულადი"],"Amount":[600],"Relationship":["სამთავრობო ჯილდო"],"Currency":["GEL"],"OwnerFirstName":["თამილა"],"OwnerLatsName":["თეიმურაზიშვილი"],"OwnerId":[954056],"Comment":{},"RelationName":["()"]}],"InOuts":[],"Enterprice":[{"LegalFormName":{},"Name":["შპს ბავშვთა ჯანმრთელობის ცენტრი"],"EnterpriseCountry":{},"EnterpriseCity":{},"EnterpriseAddress":["ალ. ალადაშვილის ქ #2"],"PartnershipForm":{},"StartDate":["16.03.2000"],"EndDateType":[0],"EndDate":[""],"EndDateName":["უვადო"],"RegistrationAgency":["თელავის რაიონის სასამართლო"],"RegisterDate":["16.03.2000"],"Share":[0],"Income":[9155],"IncomeCurrencyName":["GEL"],"AbbreviationName":{},"AbbreviationTypeId":{},"CapitalAmount":{},"CapitalAmoutCurrencyName":{},"OtherAbbreviationName":{},"PartnershipFormName":["დირექტორი"],"EnterprisePartners":[],"LinkedEnterprises":[],"OwnerFirstName":{},"OwnerLatsName":{},"OwnerId":[954056],"Comment":{},"RelationName":{}}],"LinkedEnterprice":[],"DeclarationHistory":{}}]
