[{"Id":[150711],"FirstName":["ზემინარი"],"LastName":["ბოხუა"],"Organisation":["ააიპ - „სახლი თანადგომა“"],"Position":["დირექტორი"],"BirthPlace":["საქართველო, აბაშა, სოფელი მარანი"],"BirthDate":["23.06.1953"],"VersionId":[1],"DateEdited":["09.10.2023"],"DeclarationSubmitDate":["02.10.2023"],"FamilyMembers":[{"FirstName":["არჩილ"],"LastName":["ფანცულაია"],"BirthPlace":["საქართველო, სამტრედია"],"BirthDate":["07.01.1990"],"Relationship":["შვილი"],"Comment":{}}],"Properties":[{"Address":[", , ქალაქი სამტრედია , ქუჩა რუსთაველი , N 12"],"Area":[19.5],"RegistrationDetails":{},"BlockList":{},"IsRegisteredInGeorgia":["რეგისტრირებულია საქართველოში"],"Share":[100],"PropertyType":["ავტოფარეხი"],"PurchaseForm":["მემკვიდრეობა"],"PurchaseDate":["13.12.2016"],"PurchaseYear":{},"Price":[150],"CurrencyName":["GEL"],"Details":{},"Shareholders":[],"OwnerFirstName":["არჩილ"],"OwnerLatsName":["ფანცულაია"],"OwnerId":[24337],"Comment":{},"RelationName":[""]},{"Address":[", , სამტრედიის მუნიციპალიტეტი, ქალაქი სამტრედია, კონსტიტუციას ქუჩა, N 10"],"Area":[834],"RegistrationDetails":{},"BlockList":["N01; N02- სამშენებლო დოკუმენტაციის გარეშე"],"IsRegisteredInGeorgia":["რეგისტრირებულია საქართველოში"],"Share":[100],"PropertyType":["აგარაკი"],"PurchaseForm":["მემკვიდრეობა"],"PurchaseDate":["10.08.2017"],"PurchaseYear":{},"Price":[0],"CurrencyName":{},"Details":{},"Shareholders":[],"OwnerFirstName":["ზემინარი"],"OwnerLatsName":["ბოხუა"],"OwnerId":{},"Comment":{},"RelationName":[""]},{"Address":[", , ქალაქი სამტრედია , ქუჩა N2 ავტოსადგურის ტერიტორია"],"Area":[16],"RegistrationDetails":{},"BlockList":{},"IsRegisteredInGeorgia":["რეგისტრირებულია საქართველოში"],"Share":[3.5],"PropertyType":["კომერციული ფართი"],"PurchaseForm":["მემკვიდრეობა"],"PurchaseDate":["17.03.2016"],"PurchaseYear":{},"Price":[0],"CurrencyName":{},"Details":{},"Shareholders":[{"FirstName":["თამარი"],"LastName":["ბოხუა"],"RelationShipName":[""],"Share":[0]},{"FirstName":["გულნარა"],"LastName":["ბოხუა"],"RelationShipName":[""],"Share":[0]}],"OwnerFirstName":["ზემინარი"],"OwnerLatsName":["ბოხუა"],"OwnerId":{},"Comment":{},"RelationName":[""]},{"Address":[", , ქალაქი სამტრედია , ქუჩა რუსთაველი , N 12"],"Area":[79.8],"RegistrationDetails":{},"BlockList":{},"IsRegisteredInGeorgia":["რეგისტრირებულია საქართველოში"],"Share":[100],"PropertyType":["ბინა"],"PurchaseForm":["მემკვიდრეობა"],"PurchaseDate":["21.01.2022"],"PurchaseYear":{},"Price":[0],"CurrencyName":{},"Details":{},"Shareholders":[],"OwnerFirstName":["ზემინარი"],"OwnerLatsName":["ბოხუა"],"OwnerId":{},"Comment":{},"RelationName":[""]}],"MovableProperties":[{"CarDetails":{},"Share":[100],"PropertyType":["მსუბუქი ავტომანქანა"],"PurchaseForm":["მემკვიდრეობა"],"PurchaseDate":["16.01.2023"],"PurchaseYear":{},"Price":[150],"CurrencyName":["GEL"],"Details":["მსუბუქი ავტომობილი"],"Shareholders":[],"OwnerFirstName":["ზემინარი"],"OwnerLatsName":["ბოხუა"],"OwnerId":{},"Comment":{},"RelationName":[""]}],"Securities":[],"BankAccounts":[{"BankName":["\"საქართველოს ბანკი\""],"AccountType":["სახელფასო"],"Type":[1],"Currency":["GEL"],"Amount":[9],"OwnerFirstName":["არჩილ"],"OwnerLatsName":["ფანცულაია"],"OwnerId":[24337],"Comment":{},"RelationName":[""]},{"BankName":["\"თი–ბი–სი ბანკი\""],"AccountType":["სახელფასო"],"Type":[1],"Currency":["GEL"],"Amount":[4],"OwnerFirstName":["ზემინარი"],"OwnerLatsName":["ბოხუა"],"OwnerId":{},"Comment":{},"RelationName":[""]},{"BankName":["\"ლიბერთი ბანკი\""],"AccountType":["საპენსიო"],"Type":[1],"Currency":["GEL"],"Amount":[2],"OwnerFirstName":["ზემინარი"],"OwnerLatsName":["ბოხუა"],"OwnerId":{},"Comment":{},"RelationName":[""]}],"Cashes":[],"Jobs":[{"Organisation":["ქუთაისის აეროპორტი"],"Position":["უშიშროების თანამშრომელი"],"Amount":[8400],"Currency":["GEL"],"StartDate":["01.01.2021"],"EndDate":["31.12.2021"],"IsSecret":[false],"OwnerFirstName":["არჩილ"],"OwnerLatsName":["ფანცულაია"],"OwnerId":[24337],"Comment":{},"RelationName":[""]},{"Organisation":["ააიპ სახლი თანადგომა"],"Position":["დირექტორი"],"Amount":[13320],"Currency":["GEL"],"StartDate":["01.01.2021"],"EndDate":["31.12.2021"],"IsSecret":[false],"OwnerFirstName":["ზემინარი"],"OwnerLatsName":["ბოხუა"],"OwnerId":{},"Comment":{},"RelationName":[""]},{"Organisation":["სახლი თანადგომა"],"Position":["ააიპ. სახლი თანადგომას დირექტორი"],"Amount":[9783.43],"Currency":["GEL"],"StartDate":["01.12.2022"],"EndDate":["30.12.2022"],"IsSecret":[false],"OwnerFirstName":["ზემინარი"],"OwnerLatsName":["ბოხუა"],"OwnerId":{},"Comment":{},"RelationName":[""]}],"Contracts":[],"Gifts":[],"InOuts":[],"Enterprice":[],"LinkedEnterprice":[],"DeclarationHistory":{"DeclarantInfoHistory":[],"FamilyMemberHistory":[],"PropertyHistory":[{"Id":[2196],"PublishDate":["/Date(1696849130637)/"],"VersionId":[0],"SignId":[34296],"StepId":[3],"ActionId":[1],"ActionName":["დამატება"],"Details":{"Address":[", , ქალაქი სამტრედია , ქუჩა რუსთაველი , N 12"],"Area":[19.5],"RegistrationDetails":{},"BlockList":{},"IsRegisteredInGeorgia":["რეგისტრირებულია საქართველოში"],"Share":[100],"PropertyType":["ავტოფარეხი"],"PurchaseForm":["მემკვიდრეობა"],"PurchaseDate":["13.12.2016"],"PurchaseYear":{},"Price":[150],"CurrencyName":["GEL"],"Details":{},"Shareholders":[],"OwnerFirstName":["არჩილ"],"OwnerLatsName":["ფანცულაია"],"OwnerId":[24337],"Comment":{},"RelationName":[""]}},{"Id":[2195],"PublishDate":["/Date(1696849130637)/"],"VersionId":[0],"SignId":[34296],"StepId":[3],"ActionId":[1],"ActionName":["დამატება"],"Details":{"Address":[", , სამტრედიის მუნიციპალიტეტი, ქალაქი სამტრედია, კონსტიტუციას ქუჩა, N 10"],"Area":[834],"RegistrationDetails":{},"BlockList":["N01; N02- სამშენებლო დოკუმენტაციის გარეშე"],"IsRegisteredInGeorgia":["რეგისტრირებულია საქართველოში"],"Share":[100],"PropertyType":["აგარაკი"],"PurchaseForm":["მემკვიდრეობა"],"PurchaseDate":["10.08.2017"],"PurchaseYear":{},"Price":[0],"CurrencyName":{},"Details":{},"Shareholders":[],"OwnerFirstName":["ზემინარი"],"OwnerLatsName":["ბოხუა"],"OwnerId":{},"Comment":{},"RelationName":[""]}},{"Id":[2194],"PublishDate":["/Date(1696849130637)/"],"VersionId":[0],"SignId":[34296],"StepId":[3],"ActionId":[1],"ActionName":["დამატება"],"Details":{"Address":[", , ქალაქი სამტრედია , ქუჩა N2 ავტოსადგურის ტერიტორია"],"Area":[16],"RegistrationDetails":{},"BlockList":{},"IsRegisteredInGeorgia":["რეგისტრირებულია საქართველოში"],"Share":[3.5],"PropertyType":["კომერციული ფართი"],"PurchaseForm":["მემკვიდრეობა"],"PurchaseDate":["17.03.2016"],"PurchaseYear":{},"Price":[0],"CurrencyName":{},"Details":{},"Shareholders":[{"FirstName":["თამარი"],"LastName":["ბოხუა"],"RelationShipName":[""],"Share":[0]},{"FirstName":["გულნარა"],"LastName":["ბოხუა"],"RelationShipName":[""],"Share":[0]}],"OwnerFirstName":["ზემინარი"],"OwnerLatsName":["ბოხუა"],"OwnerId":{},"Comment":{},"RelationName":[""]}},{"Id":[2193],"PublishDate":["/Date(1696849130637)/"],"VersionId":[0],"SignId":[34296],"StepId":[3],"ActionId":[1],"ActionName":["დამატება"],"Details":{"Address":[", , ქალაქი სამტრედია , ქუჩა რუსთაველი , N 12"],"Area":[79.8],"RegistrationDetails":{},"BlockList":{},"IsRegisteredInGeorgia":["რეგისტრირებულია საქართველოში"],"Share":[100],"PropertyType":["ბინა"],"PurchaseForm":["მემკვიდრეობა"],"PurchaseDate":["21.01.2022"],"PurchaseYear":{},"Price":[0],"CurrencyName":{},"Details":{},"Shareholders":[],"OwnerFirstName":["ზემინარი"],"OwnerLatsName":["ბოხუა"],"OwnerId":{},"Comment":{},"RelationName":[""]}}],"MovablePropertyHistory":[{"Id":[2198],"PublishDate":["/Date(1696849130653)/"],"VersionId":[0],"SignId":[34296],"StepId":[4],"ActionId":[1],"ActionName":["დამატება"],"Details":{"CarDetails":{},"Share":[100],"PropertyType":["მსუბუქი ავტომანქანა"],"PurchaseForm":["მემკვიდრეობა"],"PurchaseDate":["16.01.2023"],"PurchaseYear":{},"Price":[150],"CurrencyName":["GEL"],"Details":["მსუბუქი ავტომობილი"],"Shareholders":[],"OwnerFirstName":["ზემინარი"],"OwnerLatsName":["ბოხუა"],"OwnerId":{},"Comment":{},"RelationName":[""]}},{"Id":[2197],"PublishDate":["/Date(1696243373703)/"],"VersionId":[0],"SignId":[34296],"StepId":[4],"ActionId":[3],"ActionName":["წაშლა"],"Details":{"CarDetails":{},"Share":[100],"PropertyType":["მსუბუქი ავტომანქანა"],"PurchaseForm":["მემკვიდრეობა"],"PurchaseDate":["10.01.2023"],"PurchaseYear":{},"Price":[150],"CurrencyName":["GEL"],"Details":["ავეჯი"],"Shareholders":[],"OwnerFirstName":["ზემინარი"],"OwnerLatsName":["ბოხუა"],"OwnerId":{},"Comment":{},"RelationName":[""]}}],"SecurityHistory":[],"BankAccountHistory":[],"CashHistory":[],"EnterpriseHistory":[],"LinkedEnterpriseHistory":[],"JobHistory":[],"ContractHistory":[],"GiftHistory":[],"InOutHistory":[]}},{"Id":[142887],"FirstName":["ზემინარი"],"LastName":["ბოხუა"],"Organisation":["ააიპ - „სახლი თანადგომა“"],"Position":["დირექტორი"],"BirthPlace":["საქართველო, აბაშა, სოფელი მარანი"],"BirthDate":["23.06.1953"],"VersionId":{},"DateEdited":["18.10.2022"],"DeclarationSubmitDate":["18.10.2022"],"FamilyMembers":[{"FirstName":["არჩილ"],"LastName":["ფანცულაია"],"BirthPlace":["საქართველო, სამტრედია"],"BirthDate":["07.01.1990"],"Relationship":["შვილი"],"Comment":{}}],"Properties":[{"Address":[", , ქალაქი სამტრედია , ქუჩა რუსთაველი , N 12"],"Area":[79.8],"RegistrationDetails":{},"BlockList":{},"IsRegisteredInGeorgia":["რეგისტრირებულია საქართველოში"],"Share":[100],"PropertyType":["საცხოვრებელი სახლი"],"PurchaseForm":["ნასყიდობა"],"PurchaseDate":["21.01.2022"],"PurchaseYear":{},"Price":[23000],"CurrencyName":["GEL"],"Details":{},"Shareholders":[],"OwnerFirstName":["ზემინარი"],"OwnerLatsName":["ბოხუა"],"OwnerId":{},"Comment":{},"RelationName":[""]},{"Address":[", , ქალაქი სამტრედია ,   კონსტიტუციის ქუჩა N10"],"Area":[861],"RegistrationDetails":{},"BlockList":["N1"],"IsRegisteredInGeorgia":["რეგისტრირებულია საქართველოში"],"Share":[100],"PropertyType":["მიწის ნაკვეთი"],"PurchaseForm":["ნასყიდობა"],"PurchaseDate":["10.08.2017"],"PurchaseYear":{},"Price":[500],"CurrencyName":["GEL"],"Details":{},"Shareholders":[],"OwnerFirstName":["ზემინარი"],"OwnerLatsName":["ბოხუა"],"OwnerId":{},"Comment":{},"RelationName":[""]},{"Address":[", , ქალაქი სამტრედია , ქუჩა N2 ავტოსადგურის ტერიტორია"],"Area":[16],"RegistrationDetails":{},"BlockList":{},"IsRegisteredInGeorgia":["რეგისტრირებულია საქართველოში"],"Share":[30],"PropertyType":["კომერციული ფართი"],"PurchaseForm":["ჩუქება"],"PurchaseDate":["17.03.2016"],"PurchaseYear":{},"Price":[200],"CurrencyName":["GEL"],"Details":{},"Shareholders":[{"FirstName":["თამარი"],"LastName":["ბოხუა"],"RelationShipName":[""],"Share":[0]},{"FirstName":["გულნარა"],"LastName":["ბოხუა"],"RelationShipName":[""],"Share":[0]},{"FirstName":["თამარი"],"LastName":["ბოხუს"],"RelationShipName":[""],"Share":[0]},{"FirstName":["გულნარა"],"LastName":["ბოხუა"],"RelationShipName":[""],"Share":[0]}],"OwnerFirstName":["ზემინარი"],"OwnerLatsName":["ბოხუა"],"OwnerId":{},"Comment":{},"RelationName":[""]},{"Address":[", , ქალაქი სამტრედია , ქუჩა რუსთაველი , N 12"],"Area":[19.5],"RegistrationDetails":{},"BlockList":{},"IsRegisteredInGeorgia":["რეგისტრირებულია საქართველოში"],"Share":[100],"PropertyType":["ავტოფარეხი"],"PurchaseForm":["ნასყიდობა"],"PurchaseDate":["13.12.2016"],"PurchaseYear":{},"Price":[50],"CurrencyName":["GEL"],"Details":{},"Shareholders":[],"OwnerFirstName":["არჩილ"],"OwnerLatsName":["ფანცულაია"],"OwnerId":[24337],"Comment":{},"RelationName":[""]}],"MovableProperties":[],"Securities":[],"BankAccounts":[{"BankName":["\"საქართველოს ბანკი\""],"AccountType":["სახელფასო"],"Type":[1],"Currency":["GEL"],"Amount":[4],"OwnerFirstName":["ზემინარი"],"OwnerLatsName":["ბოხუა"],"OwnerId":{},"Comment":{},"RelationName":[""]},{"BankName":["\"საქართველოს ბანკი\""],"AccountType":["სახელფასო"],"Type":[1],"Currency":["GEL"],"Amount":[9],"OwnerFirstName":["არჩილ"],"OwnerLatsName":["ფანცულაია"],"OwnerId":[24337],"Comment":{},"RelationName":[""]}],"Cashes":[],"Jobs":[{"Organisation":["ქუთაისის აეროპორტი"],"Position":["უშიშროების თანამშრომელი"],"Amount":[8400],"Currency":["GEL"],"StartDate":["01.01.2021"],"EndDate":["31.12.2021"],"IsSecret":[false],"OwnerFirstName":["არჩილ"],"OwnerLatsName":["ფანცულაია"],"OwnerId":[24337],"Comment":{},"RelationName":[""]},{"Organisation":["ააიპ სახლი თანადგომა"],"Position":["დირექტორი"],"Amount":[13320],"Currency":["GEL"],"StartDate":["01.01.2021"],"EndDate":["31.12.2021"],"IsSecret":[false],"OwnerFirstName":["ზემინარი"],"OwnerLatsName":["ბოხუა"],"OwnerId":{},"Comment":{},"RelationName":[""]}],"Contracts":[],"Gifts":[],"InOuts":[],"Enterprice":[],"LinkedEnterprice":[],"DeclarationHistory":{"DeclarantInfoHistory":[],"FamilyMemberHistory":[],"PropertyHistory":[],"MovablePropertyHistory":[],"SecurityHistory":[],"BankAccountHistory":[],"CashHistory":[],"EnterpriseHistory":[],"LinkedEnterpriseHistory":[],"JobHistory":[],"ContractHistory":[],"GiftHistory":[],"InOutHistory":[]}},{"Id":[134945],"FirstName":["ზემინარი"],"LastName":["ბოხუა"],"Organisation":["ააიპ - „სახლი თანადგომა“"],"Position":["დირექტორი"],"BirthPlace":["საქართველო, აბაშა, სოფელი მარანი"],"BirthDate":["23.06.1953"],"VersionId":{},"DateEdited":["12.10.2021"],"DeclarationSubmitDate":["12.10.2021"],"FamilyMembers":[{"FirstName":["არჩილ"],"LastName":["ფანცულაია"],"BirthPlace":["საქართველო, სამტრედია"],"BirthDate":["07.01.1990"],"Relationship":["შვილი"],"Comment":{}}],"Properties":[{"Address":[", , ქალაქი სამტრედია , ქუჩა რუსთაველი , N 12"],"Area":[19.5],"RegistrationDetails":{},"BlockList":{},"IsRegisteredInGeorgia":["რეგისტრირებულია საქართველოში"],"Share":[100],"PropertyType":["ავტოფარეხი"],"PurchaseForm":["ნასყიდობა"],"PurchaseDate":["13.12.2016"],"PurchaseYear":{},"Price":[50],"CurrencyName":["GEL"],"Details":{},"Shareholders":[],"OwnerFirstName":["არჩილ"],"OwnerLatsName":["ფანცულაია"],"OwnerId":[24337],"Comment":{},"RelationName":[""]},{"Address":[", , ქალაქი სამტრედია , ქუჩა N2 ავტოსადგურის ტერიტორია"],"Area":[16],"RegistrationDetails":{},"BlockList":{},"IsRegisteredInGeorgia":["რეგისტრირებულია საქართველოში"],"Share":[30],"PropertyType":["კომერციული ფართი"],"PurchaseForm":["ჩუქება"],"PurchaseDate":["17.03.2016"],"PurchaseYear":{},"Price":[200],"CurrencyName":["GEL"],"Details":{},"Shareholders":[{"FirstName":["თამარი"],"LastName":["ბოხუა"],"RelationShipName":[""],"Share":[0]},{"FirstName":["გულნარა"],"LastName":["ბოხუა"],"RelationShipName":[""],"Share":[0]}],"OwnerFirstName":["ზემინარი"],"OwnerLatsName":["ბოხუა"],"OwnerId":{},"Comment":{},"RelationName":[""]},{"Address":[", , ქალაქი სამტრედია ,   კონსტიტუციის ქუჩა N10"],"Area":[861],"RegistrationDetails":{},"BlockList":["N1"],"IsRegisteredInGeorgia":["რეგისტრირებულია საქართველოში"],"Share":[100],"PropertyType":["მიწის ნაკვეთი"],"PurchaseForm":["ნასყიდობა"],"PurchaseDate":["10.08.2017"],"PurchaseYear":{},"Price":[500],"CurrencyName":["GEL"],"Details":{},"Shareholders":[],"OwnerFirstName":["ზემინარი"],"OwnerLatsName":["ბოხუა"],"OwnerId":{},"Comment":{},"RelationName":[""]}],"MovableProperties":[],"Securities":[],"BankAccounts":[{"BankName":["\"საქართველოს ბანკი\""],"AccountType":["სახელფასო"],"Type":[1],"Currency":["GEL"],"Amount":[0],"OwnerFirstName":["ზემინარი"],"OwnerLatsName":["ბოხუა"],"OwnerId":{},"Comment":{},"RelationName":[""]},{"BankName":["\"საქართველოს ბანკი\""],"AccountType":["სახელფასო"],"Type":[1],"Currency":["GEL"],"Amount":[0],"OwnerFirstName":["არჩილ"],"OwnerLatsName":["ფანცულაია"],"OwnerId":[24337],"Comment":{},"RelationName":[""]}],"Cashes":[],"Jobs":[{"Organisation":["სახლი თანადგომა"],"Position":["დირექტორი"],"Amount":[9696],"Currency":["GEL"],"StartDate":["01.01.2020"],"EndDate":["31.12.2020"],"IsSecret":[false],"OwnerFirstName":["ზემინარი"],"OwnerLatsName":["ბოხუა"],"OwnerId":{},"Comment":{},"RelationName":[""]},{"Organisation":["ქუთაისის აეროპორტი"],"Position":["უშიშროების თანამშრომელი"],"Amount":[6960],"Currency":["GEL"],"StartDate":["01.01.2020"],"EndDate":["31.12.2020"],"IsSecret":[false],"OwnerFirstName":["არჩილ"],"OwnerLatsName":["ფანცულაია"],"OwnerId":[24337],"Comment":{},"RelationName":[""]}],"Contracts":[],"Gifts":[],"InOuts":[],"Enterprice":[],"LinkedEnterprice":[],"DeclarationHistory":{"DeclarantInfoHistory":[],"FamilyMemberHistory":[],"PropertyHistory":[],"MovablePropertyHistory":[],"SecurityHistory":[],"BankAccountHistory":[],"CashHistory":[],"EnterpriseHistory":[],"LinkedEnterpriseHistory":[],"JobHistory":[],"ContractHistory":[],"GiftHistory":[],"InOutHistory":[]}},{"Id":[128463],"FirstName":["ზემინარ"],"LastName":["ბოხუა"],"Organisation":["ააიპ - „სახლი თანადგომა“"],"Position":["დირექტორი"],"BirthPlace":["საქართველო, აბაშა, სოფელი მარანი"],"BirthDate":["23.06.1953"],"VersionId":{},"DateEdited":{},"DeclarationSubmitDate":["02.10.2020"],"FamilyMembers":[{"FirstName":["არჩილ"],"LastName":["ფანცულაია"],"BirthPlace":["საქართველო, სამტრედია"],"BirthDate":["07.01.1990"],"Relationship":["შვილი"],"Comment":{}},{"FirstName":["ონისიმე"],"LastName":["ფანცულაია"],"BirthPlace":["საქართველო, მარტვილი"],"BirthDate":["18.05.1949"],"Relationship":["მეუღლე"],"Comment":{}}],"Properties":[{"Address":["საქართველო, სამტრედია, კონსტიტუციის ქ.#10"],"Area":[861],"RegistrationDetails":{},"BlockList":{},"IsRegisteredInGeorgia":{},"Share":[100],"PropertyType":["მიწის ნაკვეთი"],"PurchaseForm":["ჩუქება"],"PurchaseDate":["01.01.1900"],"PurchaseYear":[2018],"Price":[0],"CurrencyName":["GEL"],"Details":{},"Shareholders":[],"OwnerFirstName":["ზემინარ"],"OwnerLatsName":["ბოხუა"],"OwnerId":{},"Comment":{},"RelationName":[""]},{"Address":["საქართველო, სამტრედია, რუსთაველის 12/3"],"Area":[65],"RegistrationDetails":{},"BlockList":{},"IsRegisteredInGeorgia":{},"Share":[100],"PropertyType":["ბინა"],"PurchaseForm":["გადაეცა რკინიგზიდან"],"PurchaseDate":["01.01.1900"],"PurchaseYear":[1982],"Price":[0],"CurrencyName":["Maneti"],"Details":{},"Shareholders":[],"OwnerFirstName":["ონისიმე"],"OwnerLatsName":["ფანცულაია"],"OwnerId":[24338],"Comment":{},"RelationName":[""]}],"MovableProperties":[],"Securities":[],"BankAccounts":[{"BankName":["\"საქართველოს ბანკი\""],"AccountType":["სახელფასო"],"Type":[1],"Currency":["GEL"],"Amount":[8],"OwnerFirstName":["ზემინარ"],"OwnerLatsName":["ბოხუა"],"OwnerId":{},"Comment":{},"RelationName":[""]},{"BankName":["\"საქართველოს ბანკი\""],"AccountType":["სახელფასო"],"Type":[1],"Currency":["GEL"],"Amount":[0],"OwnerFirstName":["არჩილ"],"OwnerLatsName":["ფანცულაია"],"OwnerId":[24337],"Comment":{},"RelationName":[""]},{"BankName":["\"თი–ბი–სი ბანკი\""],"AccountType":["სახელფასო"],"Type":[1],"Currency":["GEL"],"Amount":[0],"OwnerFirstName":["ონისიმე"],"OwnerLatsName":["ფანცულაია"],"OwnerId":[24338],"Comment":{},"RelationName":[""]}],"Cashes":[],"Jobs":[{"Organisation":["საქართველოს შინაგან საქმეთა სამინისტრო"],"Position":["დაცვის პოლიციელი"],"Amount":[5700],"Currency":["GEL"],"StartDate":["01.01.2019"],"EndDate":["31.12.2019"],"IsSecret":[false],"OwnerFirstName":["არჩილ"],"OwnerLatsName":["ფანცულაია"],"OwnerId":[24337],"Comment":{},"RelationName":[""]},{"Organisation":["სს-საქართველოს რკინიგზა"],"Position":["დეფექტოსკოპიის წამყვანი სპეციალისტი"],"Amount":[9600],"Currency":["GEL"],"StartDate":["01.01.2019"],"EndDate":["31.12.2019"],"IsSecret":[false],"OwnerFirstName":["ონისიმე"],"OwnerLatsName":["ფანცულაია"],"OwnerId":[24338],"Comment":{},"RelationName":[""]},{"Organisation":["ააიპ - „სახლი თანადგომა“"],"Position":["დირექტორი"],"Amount":[12120],"Currency":["GEL"],"StartDate":["01.01.2019"],"EndDate":["31.12.2019"],"IsSecret":[false],"OwnerFirstName":["ზემინარ"],"OwnerLatsName":["ბოხუა"],"OwnerId":{},"Comment":{},"RelationName":[""]}],"Contracts":[],"Gifts":[],"InOuts":[],"Enterprice":[],"LinkedEnterprice":[],"DeclarationHistory":{}},{"Id":[121816],"FirstName":["ზემინარ"],"LastName":["ბოხუა"],"Organisation":["ააიპ - „სახლი თანადგომა“"],"Position":["დირექტორი"],"BirthPlace":["საქართველო, აბაშა, სოფელი მარანი"],"BirthDate":["23.06.1953"],"VersionId":{},"DateEdited":{},"DeclarationSubmitDate":["04.10.2019"],"FamilyMembers":[{"FirstName":["არჩილ"],"LastName":["ფანცულაია"],"BirthPlace":["საქართველო, სამტრედია"],"BirthDate":["07.01.1990"],"Relationship":["შვილი"],"Comment":{}},{"FirstName":["ონისიმე"],"LastName":["ფანცულაია"],"BirthPlace":["საქართველო, მარტვილი"],"BirthDate":["18.05.1949"],"Relationship":["მეუღლე"],"Comment":{}}],"Properties":[{"Address":["საქართველო, სამტრედია, კონსტიტუციის ქ.#10"],"Area":[861],"RegistrationDetails":{},"BlockList":{},"IsRegisteredInGeorgia":{},"Share":[100],"PropertyType":["მიწის ნაკვეთი"],"PurchaseForm":["ჩუქება"],"PurchaseDate":["01.01.1900"],"PurchaseYear":[2018],"Price":[0],"CurrencyName":["GEL"],"Details":{},"Shareholders":[],"OwnerFirstName":["ზემინარ"],"OwnerLatsName":["ბოხუა"],"OwnerId":{},"Comment":{},"RelationName":[""]},{"Address":["საქართველო, სამტრედია, რუსთაველის 12/3"],"Area":[65],"RegistrationDetails":{},"BlockList":{},"IsRegisteredInGeorgia":{},"Share":[100],"PropertyType":["ბინა"],"PurchaseForm":["გადაეცა რკინიგზიდან"],"PurchaseDate":["01.01.1900"],"PurchaseYear":[1982],"Price":[0],"CurrencyName":["Maneti"],"Details":{},"Shareholders":[],"OwnerFirstName":["ონისიმე"],"OwnerLatsName":["ფანცულაია"],"OwnerId":[24338],"Comment":{},"RelationName":[""]}],"MovableProperties":[],"Securities":[],"BankAccounts":[{"BankName":["\"საქართველოს ბანკი\""],"AccountType":["სახელფასო"],"Type":[1],"Currency":["GEL"],"Amount":[0],"OwnerFirstName":["ზემინარ"],"OwnerLatsName":["ბოხუა"],"OwnerId":{},"Comment":{},"RelationName":[""]},{"BankName":["\"საქართველოს ბანკი\""],"AccountType":["სახელფასო"],"Type":[1],"Currency":["GEL"],"Amount":[0],"OwnerFirstName":["არჩილ"],"OwnerLatsName":["ფანცულაია"],"OwnerId":[24337],"Comment":{},"RelationName":[""]},{"BankName":["\"თი–ბი–სი ბანკი\""],"AccountType":["სახელფასო"],"Type":[1],"Currency":["GEL"],"Amount":[0],"OwnerFirstName":["ონისიმე"],"OwnerLatsName":["ფანცულაია"],"OwnerId":[24338],"Comment":{},"RelationName":[""]}],"Cashes":[],"Jobs":[{"Organisation":["საქართველოს შინაგან საქმეთა სამინისტრო"],"Position":["დაცვის პოლიციელი"],"Amount":[5700],"Currency":["GEL"],"StartDate":["01.01.2018"],"EndDate":["31.12.2018"],"IsSecret":[false],"OwnerFirstName":["არჩილ"],"OwnerLatsName":["ფანცულაია"],"OwnerId":[24337],"Comment":{},"RelationName":[""]},{"Organisation":["სს-საქართველოს რკინიგზა"],"Position":["დეფექტოსკოპიის წამყვანი სპეციალისტი"],"Amount":[9600],"Currency":["GEL"],"StartDate":["01.01.2018"],"EndDate":["31.12.2018"],"IsSecret":[false],"OwnerFirstName":["ონისიმე"],"OwnerLatsName":["ფანცულაია"],"OwnerId":[24338],"Comment":{},"RelationName":[""]},{"Organisation":["ააიპ - „სახლი თანადგომა“"],"Position":["დირექტორი"],"Amount":[12120],"Currency":["GEL"],"StartDate":["01.01.2018"],"EndDate":["31.12.2018"],"IsSecret":[false],"OwnerFirstName":["ზემინარ"],"OwnerLatsName":["ბოხუა"],"OwnerId":{},"Comment":{},"RelationName":[""]}],"Contracts":[],"Gifts":[],"InOuts":[],"Enterprice":[],"LinkedEnterprice":[],"DeclarationHistory":{}},{"Id":[114316],"FirstName":["ზემინარ"],"LastName":["ბოხუა"],"Organisation":["ააიპ - „სახლი თანადგომა“"],"Position":["დირექტორი"],"BirthPlace":["საქართველო, აბაშა, სოფელი მარანი"],"BirthDate":["23.06.1953"],"VersionId":{},"DateEdited":{},"DeclarationSubmitDate":["02.10.2018"],"FamilyMembers":[{"FirstName":["არჩილ"],"LastName":["ფანცულაია"],"BirthPlace":["საქართველო, სამტრედია"],"BirthDate":["07.01.1990"],"Relationship":["შვილი"],"Comment":{}},{"FirstName":["ონისიმე"],"LastName":["ფანცულაია"],"BirthPlace":["საქართველო, მარტვილი"],"BirthDate":["18.05.1949"],"Relationship":["მეუღლე"],"Comment":{}}],"Properties":[{"Address":["საქართველო, სამტრედია, კონსტიტუციის ქ.#10"],"Area":[861],"RegistrationDetails":{},"BlockList":{},"IsRegisteredInGeorgia":{},"Share":[100],"PropertyType":["მიწის ნაკვეთი"],"PurchaseForm":["ჩუქება"],"PurchaseDate":["01.01.1900"],"PurchaseYear":[2018],"Price":[0],"CurrencyName":["GEL"],"Details":{},"Shareholders":[],"OwnerFirstName":["ზემინარ"],"OwnerLatsName":["ბოხუა"],"OwnerId":{},"Comment":{},"RelationName":[""]},{"Address":["საქართველო, სამტრედია, რუსთაველის 12/3"],"Area":[65],"RegistrationDetails":{},"BlockList":{},"IsRegisteredInGeorgia":{},"Share":[100],"PropertyType":["ბინა"],"PurchaseForm":["გადაეცა რკინიგზიდან"],"PurchaseDate":["01.01.1900"],"PurchaseYear":[1982],"Price":[0],"CurrencyName":["Maneti"],"Details":{},"Shareholders":[],"OwnerFirstName":["ონისიმე"],"OwnerLatsName":["ფანცულაია"],"OwnerId":[24338],"Comment":{},"RelationName":[""]}],"MovableProperties":[{"CarDetails":{},"Share":[100],"PropertyType":["მსუბუქი ავტომანქანა"],"PurchaseForm":["ნასყიდობა"],"PurchaseDate":["01.01.1900"],"PurchaseYear":[2016],"Price":[3000],"CurrencyName":["USD"],"Details":["MERCEDES"],"Shareholders":[],"OwnerFirstName":["ონისიმე"],"OwnerLatsName":["ფანცულაია"],"OwnerId":[24338],"Comment":{},"RelationName":[""]}],"Securities":[],"BankAccounts":[{"BankName":["\"საქართველოს ბანკი\""],"AccountType":["სახელფასო"],"Type":[1],"Currency":["GEL"],"Amount":[0],"OwnerFirstName":["ზემინარ"],"OwnerLatsName":["ბოხუა"],"OwnerId":{},"Comment":{},"RelationName":[""]},{"BankName":["\"საქართველოს ბანკი\""],"AccountType":["სახელფასო"],"Type":[1],"Currency":["GEL"],"Amount":[0],"OwnerFirstName":["არჩილ"],"OwnerLatsName":["ფანცულაია"],"OwnerId":[24337],"Comment":{},"RelationName":[""]},{"BankName":["\"თი–ბი–სი ბანკი\""],"AccountType":["სახელფასო"],"Type":[1],"Currency":["GEL"],"Amount":[0],"OwnerFirstName":["ონისიმე"],"OwnerLatsName":["ფანცულაია"],"OwnerId":[24338],"Comment":{},"RelationName":[""]}],"Cashes":[],"Jobs":[{"Organisation":["საქართველოს შინაგან საქმეთა სამინისტრო"],"Position":["დაცვის პოლიციელი"],"Amount":[5700],"Currency":["GEL"],"StartDate":["01.01.2017"],"EndDate":["31.12.2017"],"IsSecret":[false],"OwnerFirstName":["არჩილ"],"OwnerLatsName":["ფანცულაია"],"OwnerId":[24337],"Comment":{},"RelationName":[""]},{"Organisation":["სს-საქართველოს რკინიგზა"],"Position":["დეფექტოსკოპიის წამყვანი სპეციალისტი"],"Amount":[9600],"Currency":["GEL"],"StartDate":["01.01.2017"],"EndDate":["31.12.2017"],"IsSecret":[false],"OwnerFirstName":["ონისიმე"],"OwnerLatsName":["ფანცულაია"],"OwnerId":[24338],"Comment":{},"RelationName":[""]},{"Organisation":["ააიპ - „სახლი თანადგომა“"],"Position":["დირექტორი"],"Amount":[12120],"Currency":["GEL"],"StartDate":["01.01.2017"],"EndDate":["31.12.2017"],"IsSecret":[false],"OwnerFirstName":["ზემინარ"],"OwnerLatsName":["ბოხუა"],"OwnerId":{},"Comment":{},"RelationName":[""]}],"Contracts":[],"Gifts":[],"InOuts":[],"Enterprice":[],"LinkedEnterprice":[],"DeclarationHistory":{}},{"Id":[106556],"FirstName":["ზემინარ"],"LastName":["ბოხუა"],"Organisation":["ააიპ - „სახლი თანადგომა“"],"Position":["დირექტორი"],"BirthPlace":["საქართველო, აბაშა, სოფელი მარანი"],"BirthDate":["23.06.1953"],"VersionId":{},"DateEdited":{},"DeclarationSubmitDate":["06.10.2017"],"FamilyMembers":[{"FirstName":["არჩილ"],"LastName":["ფანცულაია"],"BirthPlace":["საქართველო, სამტრედია"],"BirthDate":["07.01.1990"],"Relationship":["შვილი"],"Comment":{}},{"FirstName":["ონისიმე"],"LastName":["ფანცულაია"],"BirthPlace":["საქართველო, მარტვილი"],"BirthDate":["18.05.1949"],"Relationship":["მეუღლე"],"Comment":{}}],"Properties":[{"Address":["საქართველო, სამტრედია, რუსთაველის 12/3"],"Area":[65],"RegistrationDetails":{},"BlockList":{},"IsRegisteredInGeorgia":{},"Share":[100],"PropertyType":["ბინა"],"PurchaseForm":["გადაეცა რკინიგზიდან"],"PurchaseDate":["01.01.1900"],"PurchaseYear":[1982],"Price":[0],"CurrencyName":["Maneti"],"Details":{},"Shareholders":[],"OwnerFirstName":["ონისიმე"],"OwnerLatsName":["ფანცულაია"],"OwnerId":[24338],"Comment":{},"RelationName":[""]}],"MovableProperties":[{"CarDetails":{},"Share":[100],"PropertyType":["მსუბუქი ავტომანქანა"],"PurchaseForm":["ნასყიდობა"],"PurchaseDate":["01.01.1900"],"PurchaseYear":[2016],"Price":[3000],"CurrencyName":["USD"],"Details":["MERCEDES"],"Shareholders":[],"OwnerFirstName":["ონისიმე"],"OwnerLatsName":["ფანცულაია"],"OwnerId":[24338],"Comment":{},"RelationName":[""]}],"Securities":[],"BankAccounts":[],"Cashes":[],"Jobs":[{"Organisation":["საქართველოს შინაგან საქმეთა სამინისტრო"],"Position":["დაცვის პოლიციელი"],"Amount":[4800],"Currency":["GEL"],"StartDate":["01.01.2016"],"EndDate":["31.12.2016"],"IsSecret":[false],"OwnerFirstName":["არჩილ"],"OwnerLatsName":["ფანცულაია"],"OwnerId":[24337],"Comment":{},"RelationName":[""]},{"Organisation":["სს-საქართველოს რკინიგზა"],"Position":["დეფექტოსკოპიის წამყვანი სპეციალისტი"],"Amount":[9600],"Currency":["GEL"],"StartDate":["01.01.2016"],"EndDate":["31.12.2016"],"IsSecret":[false],"OwnerFirstName":["ონისიმე"],"OwnerLatsName":["ფანცულაია"],"OwnerId":[24338],"Comment":{},"RelationName":[""]},{"Organisation":["ააიპ - „სახლი თანადგომა“"],"Position":["დირექტორი"],"Amount":[12120],"Currency":["GEL"],"StartDate":["01.01.2016"],"EndDate":["31.12.2016"],"IsSecret":[false],"OwnerFirstName":["ზემინარ"],"OwnerLatsName":["ბოხუა"],"OwnerId":{},"Comment":{},"RelationName":[""]}],"Contracts":[],"Gifts":[],"InOuts":[],"Enterprice":[],"LinkedEnterprice":[],"DeclarationHistory":{}},{"Id":[964843],"FirstName":["ზემინარ"],"LastName":["ბოხუა"],"Organisation":["ააიპ - „სახლი თანადგომა“"],"Position":["დირექტორი"],"BirthPlace":["საქართველო, აბაშა, სოფელი მარანი"],"BirthDate":["23.06.1953"],"VersionId":{},"DateEdited":{},"DeclarationSubmitDate":["31.10.2016"],"FamilyMembers":[{"FirstName":["არჩილ"],"LastName":["ფანცულაია"],"BirthPlace":["საქართველო, სამტრედია, "],"BirthDate":["07.01.1990"],"Relationship":["შვილი"],"Comment":{}},{"FirstName":["ონისიმე"],"LastName":["ფანცულაია"],"BirthPlace":["საქართველო, მარტვილი, "],"BirthDate":["18.05.1949"],"Relationship":["მეუღლე"],"Comment":{}}],"Properties":[{"Address":["საქართველო, სამტრედია, რუსთაველის 12/3"],"Area":[65],"RegistrationDetails":{},"BlockList":{},"IsRegisteredInGeorgia":{},"Share":[100],"PropertyType":["ბინა"],"PurchaseForm":[""],"PurchaseDate":[""],"PurchaseYear":{},"Price":[0],"CurrencyName":["GEL"],"Details":{},"Shareholders":[],"OwnerFirstName":["ონისიმე"],"OwnerLatsName":["ფანცულაია"],"OwnerId":[1007764],"Comment":{},"RelationName":[""]}],"MovableProperties":[],"Securities":[],"BankAccounts":[{"BankName":["საქართველოს ბანკი"],"AccountType":["ხელფასი"],"Type":[1],"Currency":["GEL"],"Amount":[240],"OwnerFirstName":["ზემინარ"],"OwnerLatsName":["ბოხუა"],"OwnerId":[1007474],"Comment":{},"RelationName":["()"]},{"BankName":["საქართველოს ბანკი"],"AccountType":["ხელფასი"],"Type":[1],"Currency":["GEL"],"Amount":[0],"OwnerFirstName":["არჩილ"],"OwnerLatsName":["ფანცულაია"],"OwnerId":[1007763],"Comment":{},"RelationName":[""]},{"BankName":["რესპუბლიკა ბანკი"],"AccountType":["ხელფასი"],"Type":[1],"Currency":["GEL"],"Amount":[0],"OwnerFirstName":["ონისიმე"],"OwnerLatsName":["ფანცულაია"],"OwnerId":[1007764],"Comment":{},"RelationName":[""]}],"Cashes":[],"Jobs":[{"Organisation":["საქართველოს შინაგან საქმეთა სამინისტრო"],"Position":["საქართველოს შინაგან საქმეთა სამინისტრო"],"Amount":[4800],"Currency":["GEL"],"StartDate":[""],"EndDate":[""],"IsSecret":[false],"OwnerFirstName":["არჩილ"],"OwnerLatsName":["ფანცულაია"],"OwnerId":[1007763],"Comment":{},"RelationName":[""]},{"Organisation":["სს-საქართველოს რკინიგზა"],"Position":["სს-საქართველოს რკინიგზა"],"Amount":[9600],"Currency":["GEL"],"StartDate":[""],"EndDate":[""],"IsSecret":[false],"OwnerFirstName":["ონისიმე"],"OwnerLatsName":["ფანცულაია"],"OwnerId":[1007764],"Comment":{},"RelationName":[""]},{"Organisation":["ააიპ - „სახლი თანადგომა“"],"Position":["ააიპ - „სახლი თანადგომა“"],"Amount":[12120],"Currency":["GEL"],"StartDate":[""],"EndDate":[""],"IsSecret":[false],"OwnerFirstName":["ზემინარ"],"OwnerLatsName":["ბოხუა"],"OwnerId":[1007474],"Comment":{},"RelationName":["()"]}],"Contracts":[],"Gifts":[],"InOuts":[],"Enterprice":[],"LinkedEnterprice":[],"DeclarationHistory":{}},{"Id":[958030],"FirstName":["ზემინარ"],"LastName":["ბოხუა"],"Organisation":["ააიპ - „სახლი თანადგომა“"],"Position":["დირექტორი"],"BirthPlace":["საქართველო, აბაშა, სოფელი მარანი"],"BirthDate":["23.06.1953"],"VersionId":{},"DateEdited":{},"DeclarationSubmitDate":["30.10.2015"],"FamilyMembers":[{"FirstName":["არჩილ"],"LastName":["ფანცულაია"],"BirthPlace":["საქართველო, სამტრედია, "],"BirthDate":["07.01.1990"],"Relationship":["შვილი"],"Comment":{}},{"FirstName":["ონისიმე"],"LastName":["ფანცულაია"],"BirthPlace":["საქართველო, მარტვილი, "],"BirthDate":["18.05.1949"],"Relationship":["მეუღლე"],"Comment":{}}],"Properties":[{"Address":["საქართველო, სამტრედია, რუსთაველის 12/3"],"Area":[65],"RegistrationDetails":{},"BlockList":{},"IsRegisteredInGeorgia":{},"Share":[100],"PropertyType":["ბინა"],"PurchaseForm":[""],"PurchaseDate":[""],"PurchaseYear":{},"Price":[0],"CurrencyName":["GEL"],"Details":{},"Shareholders":[],"OwnerFirstName":["ონისიმე"],"OwnerLatsName":["ფანცულაია"],"OwnerId":[1007764],"Comment":{},"RelationName":[""]}],"MovableProperties":[],"Securities":[],"BankAccounts":[{"BankName":["საქართველოს ბანკი"],"AccountType":["ხელფასი"],"Type":[1],"Currency":["GEL"],"Amount":[240],"OwnerFirstName":["ზემინარ"],"OwnerLatsName":["ბოხუა"],"OwnerId":[1007474],"Comment":{},"RelationName":["()"]},{"BankName":["საქართველოს ბანკი"],"AccountType":["ხელფასი"],"Type":[1],"Currency":["GEL"],"Amount":[0],"OwnerFirstName":["არჩილ"],"OwnerLatsName":["ფანცულაია"],"OwnerId":[1007763],"Comment":{},"RelationName":[""]},{"BankName":["რესპუბლიკა ბანკი"],"AccountType":["ხელფასი"],"Type":[1],"Currency":["GEL"],"Amount":[0],"OwnerFirstName":["ონისიმე"],"OwnerLatsName":["ფანცულაია"],"OwnerId":[1007764],"Comment":{},"RelationName":[""]}],"Cashes":[],"Jobs":[{"Organisation":["საქართველოს შინაგან საქმეთა სამინისტრო"],"Position":["საქართველოს შინაგან საქმეთა სამინისტრო"],"Amount":[4800],"Currency":["GEL"],"StartDate":[""],"EndDate":[""],"IsSecret":[false],"OwnerFirstName":["არჩილ"],"OwnerLatsName":["ფანცულაია"],"OwnerId":[1007763],"Comment":{},"RelationName":[""]},{"Organisation":["სს-საქართველოს რკინიგზა"],"Position":["სს-საქართველოს რკინიგზა"],"Amount":[9600],"Currency":["GEL"],"StartDate":[""],"EndDate":[""],"IsSecret":[false],"OwnerFirstName":["ონისიმე"],"OwnerLatsName":["ფანცულაია"],"OwnerId":[1007764],"Comment":{},"RelationName":[""]},{"Organisation":["ააიპ - „სახლი თანადგომა“"],"Position":["ააიპ - „სახლი თანადგომა“"],"Amount":[12120],"Currency":["GEL"],"StartDate":[""],"EndDate":[""],"IsSecret":[false],"OwnerFirstName":["ზემინარ"],"OwnerLatsName":["ბოხუა"],"OwnerId":[1007474],"Comment":{},"RelationName":["()"]}],"Contracts":[],"Gifts":[],"InOuts":[],"Enterprice":[],"LinkedEnterprice":[],"DeclarationHistory":{}}]
